Workbook

Sheet Books (2026)
A1: Title | B1: Format | C1: Pages | D1: Remain | E1: Active | F1: =G1+1 -> 46387 | G1: =H1+1 -> 46386 | H1: =I1+1 -> 46385 | I1: =J1+1 -> 46384 | J1: =K1+1 -> 46383 | K1: =L1+1 -> 46382 | L1: =M1+1 -> 46381 | M1: =N1+1 -> 46380 | ... NE1: =NF1+1 -> 46024 | NF1: 46023
A2: books finished YTD | F2: {=IF(TODAY() >= F$1, SUM(N($C5:$C39=F5:F39)), "")} | G2: {=IF(TODAY() >= G$1, SUM(N($C5:$C39=G5:G39)), "")} | H2: {=IF(TODAY() >= H$1, SUM(N($C5:$C39=H5:H39)), "")} | I2: {=IF(TODAY() >= I$1, SUM(N($C5:$C39=I5:I39)), "")} | J2: {=IF(TODAY() >= J$1, SUM(N($C5:$C39=J5:J39)), "")} | K2: {=IF(TODAY() >= K$1, SUM(N($C5:$C39=K5:K39)), "")} | L2: {=IF(TODAY() >= L$1, SUM(N($C5:$C39=L5:L39)), "")} | M2: {=IF(TODAY() >= M$1, SUM(N($C5:$C39=M5:M39)), "")} | ... AI2: {=IF(TODAY() >= AI$1, SUM(N($C5:$C39=AI5:AI39)), "")} | AJ2: {=IF(TODAY() >= AJ$1, SUM(N($C6:$C39=AJ6:AJ39)), "")} | AK2: {=IF(TODAY() >= AK$1, SUM(N($C6:$C39=AK6:AK39)), "")} | AL2: {=IF(TODAY() >= AL$1, SUM(N($C6:$C39=AL6:AL39)), "")} | AM2: {=IF(TODAY() >= AM$1, SUM(N($C6:$C39=AM6:AM39)), "")} | AN2: {=IF(TODAY() >= AN$1, SUM(N($C6:$C39=AN6:AN39)), "")} | AO2: {=IF(TODAY() >= AO$1, SUM(N($C6:$C39=AO6:AO39)), "")} | AP2: {=IF(TODAY() >= AP$1, SUM(N($C6:$C39=AP6:AP39)), "")} | AQ2: {=IF(TODAY() >= AQ$1, SUM(N($C6:$C39=AQ6:AQ39)), "")} | ... NF2: {=IF(TODAY() >= NF$1, SUM(N($C6:$C39=NF6:NF39)), "")} -> 8
A3: pages read today | F3: =IF(TODAY() >= F$1, SUMIFS(F:F, $C:$C, "<>") - SUMIFS(#REF!, $C:$C, "<>") - 1, "") | G3: =IF(TODAY() >= G$1, SUMIFS(G:G, $C:$C, "<>") - SUMIFS(#REF!, $C:$C, "<>") - 1, "") | H3: =IF(TODAY() >= H$1, SUMIFS(H:H, $C:$C, "<>") - SUMIFS(#REF!, $C:$C, "<>") - 1, "") | I3: =IF(TODAY() >= I$1, SUMIFS(I:I, $C:$C, "<>") - SUMIFS(#REF!, $C:$C, "<>") - 1, "") | J3: =IF(TODAY() >= J$1, SUMIFS(J:J, $C:$C, "<>") - SUMIFS(#REF!, $C:$C, "<>") - 1, "") | K3: =IF(TODAY() >= K$1, SUMIFS(K:K, $C:$C, "<>") - SUMIFS(#REF!, $C:$C, "<>") - 1, "") | L3: =IF(TODAY() >= L$1, SUMIFS(L:L, $C:$C, "<>") - SUMIFS(#REF!, $C:$C, "<>") - 1, "") | M3: =IF(TODAY() >= M$1, SUMIFS(M:M, $C:$C, "<>") - SUMIFS(#REF!, $C:$C, "<>") - 1, "") | N3: =IF(TODAY() >= N$1, SUMIFS(N:N, $C:$C, "<>") - SUMIFS(#REF!, $C:$C, "<>") - 1, "") | O3: =IF(TODAY() >= O$1, SUMIFS(O:O, $C:$C, "<>") - SUMIFS(#REF!, $C:$C, "<>") - 1, "") | P3: =IF(TODAY() >= P$1, SUMIFS(P:P, $C:$C, "<>") - SUMIFS(#REF!, $C:$C, "<>") - 1, "") | Q3: =IF(TODAY() >= Q$1, SUMIFS(Q:Q, $C:$C, "<>") - SUMIFS(#REF!, $C:$C, "<>") - 1, "") | R3: =IF(TODAY() >= R$1, SUMIFS(R:R, $C:$C, "<>") - SUMIFS(#REF!, $C:$C, "<>") - 1, "") | S3: =IF(TODAY() >= S$1, SUMIFS(S:S, $C:$C, "<>") - SUMIFS(#REF!, $C:$C, "<>") - 1, "") | T3: =IF(TODAY() >= T$1, SUMIFS(T:T, $C:$C, "<>") - SUMIFS(#REF!, $C:$C, "<>") - 1, "") | U3: =IF(TODAY() >= U$1, SUMIFS(U:U, $C:$C, "<>") - SUMIFS(#REF!, $C:$C, "<>") - 1, "") | V3: =IF(TODAY() >= V$1, SUMIFS(V:V, $C:$C, "<>") - SUMIFS(#REF!, $C:$C, "<>") - 1, "") | W3: =IF(TODAY() >= W$1, SUMIFS(W:W, $C:$C, "<>") - SUMIFS(#REF!, $C:$C, "<>") - 1, "") | X3: =IF(TODAY() >= X$1, SUMIFS(X:X, $C:$C, "<>") - SUMIFS(#REF!, $C:$C, "<>") - 1, "") | Y3: =IF(TODAY() >= Y$1, SUMIFS(Y:Y, $C:$C, "<>") - SUMIFS(#REF!, $C:$C, "<>") - 1, "") | Z3: =IF(TODAY() >= Z$1, SUMIFS(Z:Z, $C:$C, "<>") - SUMIFS(#REF!, $C:$C, "<>") - 1, "") | AA3: =IF(TODAY() >= AA$1, SUMIFS(AA:AA, $C:$C, "<>") - SUMIFS(#REF!, $C:$C, "<>") - 1, "") | AB3: =IF(TODAY() >= AB$1, SUMIFS(AB:AB, $C:$C, "<>") - SUMIFS(#REF!, $C:$C, "<>") - 1, "") | AC3: =IF(TODAY() >= AC$1, SUMIFS(AC:AC, $C:$C, "<>") - SUMIFS(#REF!, $C:$C, "<>") - 1, "") | AD3: =IF(TODAY() >= AD$1, SUMIFS(AD:AD, $C:$C, "<>") - SUMIFS(#REF!, $C:$C, "<>") - 1, "") | AE3: =IF(TODAY() >= AE$1, SUMIFS(AE:AE, $C:$C, "<>") - SUMIFS(#REF!, $C:$C, "<>") - 1, "") | AF3: =IF(TODAY() >= AF$1, SUMIFS(AF:AF, $C:$C, "<>") - SUMIFS(#REF!, $C:$C, "<>") - 1, "") | AG3: =IF(TODAY() >= AG$1, SUMIFS(AG:AG, $C:$C, "<>") - SUMIFS(#REF!, $C:$C, "<>") - 1, "") | AH3: =IF(TODAY() >= AH$1, SUMIFS(AH:AH, $C:$C, "<>") - SUMIFS(#REF!, $C:$C, "<>") - 1, "") | AI3: =IF(TODAY() >= AI$1, SUMIFS(AI:AI, $C:$C, "<>") - SUMIFS(#REF!, $C:$C, "<>") - 1, "") | AJ3: =IF(TODAY() >= AJ$1, SUMIFS(AJ6:AJ39, $C6:$C39, "<>") - SUMIFS(AK6:AK39, $C6:$C39, "<>"), "") | AK3: =IF(TODAY() >= AK$1, SUMIFS(AK6:AK39, $C6:$C39, "<>") - SUMIFS(AL6:AL39, $C6:$C39, "<>"), "") | AL3: =IF(TODAY() >= AL$1, SUMIFS(AL6:AL39, $C6:$C39, "<>") - SUMIFS(AM6:AM39, $C6:$C39, "<>"), "") | AM3: =IF(TODAY() >= AM$1, SUMIFS(AM6:AM39, $C6:$C39, "<>") - SUMIFS(AN6:AN39, $C6:$C39, "<>"), "") | AN3: =IF(TODAY() >= AN$1, SUMIFS(AN6:AN39, $C6:$C39, "<>") - SUMIFS(AO6:AO39, $C6:$C39, "<>"), "") | AO3: =IF(TODAY() >= AO$1, SUMIFS(AO6:AO39, $C6:$C39, "<>") - SUMIFS(AP6:AP39, $C6:$C39, "<>"), "") | AP3: =IF(TODAY() >= AP$1, SUMIFS(AP6:AP39, $C6:$C39, "<>") - SUMIFS(AQ6:AQ39, $C6:$C39, "<>"), "") | AQ3: =IF(TODAY() >= AQ$1, SUMIFS(AQ6:AQ39, $C6:$C39, "<>") - SUMIFS(AR6:AR39, $C6:$C39, "<>"), "") | ... NE3: =IF(TODAY() >= NE$1, SUMIFS(NE6:NE39, $C6:$C39, "<>") - SUMIFS(NF6:NF39, $C6:$C39, "<>"), "") -> 0 | NF3: 0
A4: monthly pages read cumulative | F4: =IF(TODAY() >= F$1, SUMIFS(F3:NF3, F1:NF1, ">="&DATE(YEAR(F1), MONTH(F1), 1)), "") | G4: =IF(TODAY() >= G$1, SUMIFS(G3:NG3, G1:NG1, ">="&DATE(YEAR(G1), MONTH(G1), 1)), "") | H4: =IF(TODAY() >= H$1, SUMIFS(H3:NH3, H1:NH1, ">="&DATE(YEAR(H1), MONTH(H1), 1)), "") | I4: =IF(TODAY() >= I$1, SUMIFS(I3:NI3, I1:NI1, ">="&DATE(YEAR(I1), MONTH(I1), 1)), "") | J4: =IF(TODAY() >= J$1, SUMIFS(J3:NJ3, J1:NJ1, ">="&DATE(YEAR(J1), MONTH(J1), 1)), "") | K4: =IF(TODAY() >= K$1, SUMIFS(K3:NK3, K1:NK1, ">="&DATE(YEAR(K1), MONTH(K1), 1)), "") | L4: =IF(TODAY() >= L$1, SUMIFS(L3:NL3, L1:NL1, ">="&DATE(YEAR(L1), MONTH(L1), 1)), "") | M4: =IF(TODAY() >= M$1, SUMIFS(M3:NM3, M1:NM1, ">="&DATE(YEAR(M1), MONTH(M1), 1)), "") | ... AI4: =IF(TODAY() >= AI$1, SUMIFS(AI3:OI3, AI1:OI1, ">="&DATE(YEAR(AI1), MONTH(AI1), 1)), "") | AJ4: =IF(TODAY() >= AJ$1, AK4+AJ3, "") | AK4: =IF(TODAY() >= AK$1, AL4+AK3, "") | AL4: =IF(TODAY() >= AL$1, AM4+AL3, "") | AM4: =IF(TODAY() >= AM$1, AN4+AM3, "") | AN4: =IF(TODAY() >= AN$1, AO4+AN3, "") | AO4: =IF(TODAY() >= AO$1, AP4+AO3, "") | AP4: =IF(TODAY() >= AP$1, AQ4+AP3, "") | AQ4: =IF(TODAY() >= AQ$1, AR4+AQ3, "") | ... NE4: =IF(TODAY() >= NE$1, NF4+NE3, "") -> 0 | NF4: 0
A5: monthly goal | F5: =IF(TODAY() >= F1, (date(YEAR(F$1),MONTH(F$1)+1,1) - date(YEAR(F$1),MONTH(F$1),1)) * $B$57, "") | G5: =IF(TODAY() >= G1, (date(YEAR(G$1),MONTH(G$1)+1,1) - date(YEAR(G$1),MONTH(G$1),1)) * $B$57, "") | H5: =IF(TODAY() >= H1, (date(YEAR(H$1),MONTH(H$1)+1,1) - date(YEAR(H$1),MONTH(H$1),1)) * $B$57, "") | I5: =IF(TODAY() >= I1, (date(YEAR(I$1),MONTH(I$1)+1,1) - date(YEAR(I$1),MONTH(I$1),1)) * $B$57, "") | J5: =IF(TODAY() >= J1, (date(YEAR(J$1),MONTH(J$1)+1,1) - date(YEAR(J$1),MONTH(J$1),1)) * $B$57, "") | K5: =IF(TODAY() >= K1, (date(YEAR(K$1),MONTH(K$1)+1,1) - date(YEAR(K$1),MONTH(K$1),1)) * $B$57, "") | L5: =IF(TODAY() >= L1, (date(YEAR(L$1),MONTH(L$1)+1,1) - date(YEAR(L$1),MONTH(L$1),1)) * $B$57, "") | M5: =IF(TODAY() >= M1, (date(YEAR(M$1),MONTH(M$1)+1,1) - date(YEAR(M$1),MONTH(M$1),1)) * $B$57, "") | ... NF5: =IF(TODAY() >= NF1, (date(YEAR(NF$1),MONTH(NF$1)+1,1) - date(YEAR(NF$1),MONTH(NF$1),1)) * $B$57, "") -> 0
A6: The Happiness Trap | B6: Kindle | C6: 293 | D6: =C6 - MAX($F6:NF6) -> 222 | F6: =IF(TODAY() >= F$1, G6, "") | G6: =IF(TODAY() >= G$1, H6, "") | H6: =IF(TODAY() >= H$1, I6, "") | I6: =IF(TODAY() >= I$1, J6, "") | J6: =IF(TODAY() >= J$1, K6, "") | K6: =IF(TODAY() >= K$1, L6, "") | L6: =IF(TODAY() >= L$1, M6, "") | M6: =IF(TODAY() >= M$1, N6, "") | ... NE6: =IF(TODAY() >= NE$1, NF6, "") -> 71 | NF6: {=XLOOKUP(A6, 'Books (2025)'!A6:A39, 'Books (2025)'!F6:F39)} -> 71
A7: Getting Past Your Past | B7: Libby | C7: 352 | D7: =C7 - MAX($F7:NF7) -> 330.97101 | F7: =IF(TODAY() >= F$1, G7, "") | G7: =IF(TODAY() >= G$1, H7, "") | H7: =IF(TODAY() >= H$1, I7, "") | I7: =IF(TODAY() >= I$1, J7, "") | J7: =IF(TODAY() >= J$1, K7, "") | K7: =IF(TODAY() >= K$1, L7, "") | L7: =IF(TODAY() >= L$1, M7, "") | M7: =IF(TODAY() >= M$1, N7, "") | ... NE7: =IF(TODAY() >= NE$1, NF7, "") -> 21.028994 | NF7: {=XLOOKUP(A7, 'Books (2025)'!A7:A39, 'Books (2025)'!F7:F39)} -> 21.028994
A8: The Book of Why | B8: Kindle | C8: 419 | D8: =C8 - MAX($F8:NF8) -> 419 | F8: =IF(TODAY() >= F$1, G8, "") | G8: =IF(TODAY() >= G$1, H8, "") | H8: =IF(TODAY() >= H$1, I8, "") | I8: =IF(TODAY() >= I$1, J8, "") | J8: =IF(TODAY() >= J$1, K8, "") | K8: =IF(TODAY() >= K$1, L8, "") | L8: =IF(TODAY() >= L$1, M8, "") | M8: =IF(TODAY() >= M$1, N8, "") | ... NE8: =IF(TODAY() >= NE$1, NF8, "") -> 0 | NF8: {=XLOOKUP(A8, 'Books (2025)'!A8:A39, 'Books (2025)'!F8:F39)} -> 0
A9: Validation | C9: 414 | D9: =C9 - MAX($F9:NF9) -> 414 | F9: =IF(TODAY() >= F$1, G9, "") | G9: =IF(TODAY() >= G$1, H9, "") | H9: =IF(TODAY() >= H$1, I9, "") | I9: =IF(TODAY() >= I$1, J9, "") | J9: =IF(TODAY() >= J$1, K9, "") | K9: =IF(TODAY() >= K$1, L9, "") | L9: =IF(TODAY() >= L$1, M9, "") | M9: =IF(TODAY() >= M$1, N9, "") | ... NE9: =IF(TODAY() >= NE$1, NF9, "") -> 0 | NF9: {=XLOOKUP(A9, 'Books (2025)'!A9:A39, 'Books (2025)'!F9:F39)} -> 0
A10: The Real Happy Pill | C10: 414 | D10: =C10 - MAX($F10:NF10) -> 414 | F10: =IF(TODAY() >= F$1, G10, "") | G10: =IF(TODAY() >= G$1, H10, "") | H10: =IF(TODAY() >= H$1, I10, "") | I10: =IF(TODAY() >= I$1, J10, "") | J10: =IF(TODAY() >= J$1, K10, "") | K10: =IF(TODAY() >= K$1, L10, "") | L10: =IF(TODAY() >= L$1, M10, "") | M10: =IF(TODAY() >= M$1, N10, "") | ... NE10: =IF(TODAY() >= NE$1, NF10, "") -> 0 | NF10: {=XLOOKUP(A10, 'Books (2025)'!A10:A39, 'Books (2025)'!F10:F39)} -> 0
A11: The Body Keeps the Score | B11: Nook | C11: 414 | D11: =C11 - MAX($F11:NF11) -> 414 | F11: =IF(TODAY() >= F$1, G11, "") | G11: =IF(TODAY() >= G$1, H11, "") | H11: =IF(TODAY() >= H$1, I11, "") | I11: =IF(TODAY() >= I$1, J11, "") | J11: =IF(TODAY() >= J$1, K11, "") | K11: =IF(TODAY() >= K$1, L11, "") | L11: =IF(TODAY() >= L$1, M11, "") | M11: =IF(TODAY() >= M$1, N11, "") | ... NE11: =IF(TODAY() >= NE$1, NF11, "") -> 0 | NF11: {=XLOOKUP(A11, 'Books (2025)'!A11:A39, 'Books (2025)'!F11:F39)} -> 0
A12: Tapping In | C12: 414 | D12: =C12 - MAX($F12:NF12) -> 414 | F12: =IF(TODAY() >= F$1, G12, "") | G12: =IF(TODAY() >= G$1, H12, "") | H12: =IF(TODAY() >= H$1, I12, "") | I12: =IF(TODAY() >= I$1, J12, "") | J12: =IF(TODAY() >= J$1, K12, "") | K12: =IF(TODAY() >= K$1, L12, "") | L12: =IF(TODAY() >= L$1, M12, "") | M12: =IF(TODAY() >= M$1, N12, "") | ... NE12: =IF(TODAY() >= NE$1, NF12, "") -> 0 | NF12: {=XLOOKUP(A12, 'Books (2025)'!A12:A39, 'Books (2025)'!F12:F39)} -> 0
A13: Mrs. Dalloway | C13: 414 | D13: =C13 - MAX($F13:NF13) -> 414 | F13: =IF(TODAY() >= F$1, G13, "") | G13: =IF(TODAY() >= G$1, H13, "") | H13: =IF(TODAY() >= H$1, I13, "") | I13: =IF(TODAY() >= I$1, J13, "") | J13: =IF(TODAY() >= J$1, K13, "") | K13: =IF(TODAY() >= K$1, L13, "") | L13: =IF(TODAY() >= L$1, M13, "") | M13: =IF(TODAY() >= M$1, N13, "") | ... NE13: =IF(TODAY() >= NE$1, NF13, "") -> 0 | NF13: {=XLOOKUP(A13, 'Books (2025)'!A13:A39, 'Books (2025)'!F13:F39)} -> 0
A14: Hold Me Tight | B14: Libby | C14: 414 | D14: =C14 - MAX($F14:NF14) -> 414 | F14: =IF(TODAY() >= F$1, G14, "") | G14: =IF(TODAY() >= G$1, H14, "") | H14: =IF(TODAY() >= H$1, I14, "") | I14: =IF(TODAY() >= I$1, J14, "") | J14: =IF(TODAY() >= J$1, K14, "") | K14: =IF(TODAY() >= K$1, L14, "") | L14: =IF(TODAY() >= L$1, M14, "") | M14: =IF(TODAY() >= M$1, N14, "") | ... NE14: =IF(TODAY() >= NE$1, NF14, "") -> 0 | NF14: {=XLOOKUP(A14, 'Books (2025)'!A14:A39, 'Books (2025)'!F14:F39)} -> 0
A15: DBT Workbook for Narcissistic Abuse & Gaslighting | B15: Nook | C15: 414 | D15: =C15 - MAX($F15:NF15) -> 414 | F15: =IF(TODAY() >= F$1, G15, "") | G15: =IF(TODAY() >= G$1, H15, "") | H15: =IF(TODAY() >= H$1, I15, "") | I15: =IF(TODAY() >= I$1, J15, "") | J15: =IF(TODAY() >= J$1, K15, "") | K15: =IF(TODAY() >= K$1, L15, "") | L15: =IF(TODAY() >= L$1, M15, "") | M15: =IF(TODAY() >= M$1, N15, "") | ... NE15: =IF(TODAY() >= NE$1, NF15, "") -> 0 | NF15: {=XLOOKUP(A15, 'Books (2025)'!A15:A39, 'Books (2025)'!F15:F39)} -> 0
A16: CPTSD Workbook | B16: Kindle | C16: 414 | D16: =C16 - MAX($F16:NF16) -> 414 | F16: =IF(TODAY() >= F$1, G16, "") | G16: =IF(TODAY() >= G$1, H16, "") | H16: =IF(TODAY() >= H$1, I16, "") | I16: =IF(TODAY() >= I$1, J16, "") | J16: =IF(TODAY() >= J$1, K16, "") | K16: =IF(TODAY() >= K$1, L16, "") | L16: =IF(TODAY() >= L$1, M16, "") | M16: =IF(TODAY() >= M$1, N16, "") | ... NE16: =IF(TODAY() >= NE$1, NF16, "") -> 0 | NF16: {=XLOOKUP(A16, 'Books (2025)'!A16:A39, 'Books (2025)'!F16:F39)} -> 0
A17: It's Not You | B17: Libby | C17: 368 | D17: =C17 - MAX($F17:NF17) -> 368 | F17: =IF(TODAY() >= F$1, G17, "") | G17: =IF(TODAY() >= G$1, H17, "") | H17: =IF(TODAY() >= H$1, I17, "") | I17: =IF(TODAY() >= I$1, J17, "") | J17: =IF(TODAY() >= J$1, K17, "") | K17: =IF(TODAY() >= K$1, L17, "") | L17: =IF(TODAY() >= L$1, M17, "") | M17: =IF(TODAY() >= M$1, N17, "") | ... NE17: =IF(TODAY() >= NE$1, NF17, "") -> 0 | NF17: {=XLOOKUP(A17, 'Books (2025)'!A17:A39, 'Books (2025)'!F17:F39)} -> 0
A18: Complex PTSD | B18: Kindle | C18: 341 | D18: =C18 - MAX($F18:NF18) -> 339 | F18: =IF(TODAY() >= F$1, G18, "") | G18: =IF(TODAY() >= G$1, H18, "") | H18: =IF(TODAY() >= H$1, I18, "") | I18: =IF(TODAY() >= I$1, J18, "") | J18: =IF(TODAY() >= J$1, K18, "") | K18: =IF(TODAY() >= K$1, L18, "") | L18: =IF(TODAY() >= L$1, M18, "") | M18: =IF(TODAY() >= M$1, N18, "") | ... NE18: =IF(TODAY() >= NE$1, NF18, "") -> 2 | NF18: {=XLOOKUP(A18, 'Books (2025)'!A18:A39, 'Books (2025)'!F18:F39)} -> 2
A19: The (Mis)behavior of Markets | B19: Nook | C19: 307 | D19: =C19 - MAX($F19:NF19) -> 307 | F19: =IF(TODAY() >= F$1, G19, "") | G19: =IF(TODAY() >= G$1, H19, "") | H19: =IF(TODAY() >= H$1, I19, "") | I19: =IF(TODAY() >= I$1, J19, "") | J19: =IF(TODAY() >= J$1, K19, "") | K19: =IF(TODAY() >= K$1, L19, "") | L19: =IF(TODAY() >= L$1, M19, "") | M19: =IF(TODAY() >= M$1, N19, "") | ... NE19: =IF(TODAY() >= NE$1, NF19, "") -> 0 | NF19: {=XLOOKUP(A19, 'Books (2025)'!A19:A39, 'Books (2025)'!F19:F39)} -> 0
A20: What My Bones Know | B20: Libby | C20: 352 | D20: =C20 - MAX($F20:NF20) -> 305 | F20: =IF(TODAY() >= F$1, G20, "") | G20: =IF(TODAY() >= G$1, H20, "") | H20: =IF(TODAY() >= H$1, I20, "") | I20: =IF(TODAY() >= I$1, J20, "") | J20: =IF(TODAY() >= J$1, K20, "") | K20: =IF(TODAY() >= K$1, L20, "") | L20: =IF(TODAY() >= L$1, M20, "") | M20: =IF(TODAY() >= M$1, N20, "") | ... NE20: =IF(TODAY() >= NE$1, NF20, "") -> 47 | NF20: {=XLOOKUP(A20, 'Books (2025)'!A20:A39, 'Books (2025)'!F20:F39)} -> 47
A21: The Manager's Path | B21: Kindle | C21: 219 | D21: =C21 - MAX($F21:NF21) -> 219 | F21: =IF(TODAY() >= F$1, G21, "") | G21: =IF(TODAY() >= G$1, H21, "") | H21: =IF(TODAY() >= H$1, I21, "") | I21: =IF(TODAY() >= I$1, J21, "") | J21: =IF(TODAY() >= J$1, K21, "") | K21: =IF(TODAY() >= K$1, L21, "") | L21: =IF(TODAY() >= L$1, M21, "") | M21: =IF(TODAY() >= M$1, N21, "") | ... NE21: =IF(TODAY() >= NE$1, NF21, "") -> 0 | NF21: {=XLOOKUP(A21, 'Books (2025)'!A21:A39, 'Books (2025)'!F21:F39)} -> 0
A22: High Output Management | B22: Nook | C22: 215 | D22: =C22 - MAX($F22:NF22) -> 215 | F22: =IF(TODAY() >= F$1, G22, "") | G22: =IF(TODAY() >= G$1, H22, "") | H22: =IF(TODAY() >= H$1, I22, "") | I22: =IF(TODAY() >= I$1, J22, "") | J22: =IF(TODAY() >= J$1, K22, "") | K22: =IF(TODAY() >= K$1, L22, "") | L22: =IF(TODAY() >= L$1, M22, "") | M22: =IF(TODAY() >= M$1, N22, "") | ... NE22: =IF(TODAY() >= NE$1, NF22, "") -> 0 | NF22: {=XLOOKUP(A22, 'Books (2025)'!A22:A39, 'Books (2025)'!F22:F39)} -> 0
A23: Measure What Matters | B23: Nook | C23: 298 | D23: =C23 - MAX($F23:NF23) -> 204 | F23: =IF(TODAY() >= F$1, G23, "") | G23: =IF(TODAY() >= G$1, H23, "") | H23: =IF(TODAY() >= H$1, I23, "") | I23: =IF(TODAY() >= I$1, J23, "") | J23: =IF(TODAY() >= J$1, K23, "") | K23: =IF(TODAY() >= K$1, L23, "") | L23: =IF(TODAY() >= L$1, M23, "") | M23: =IF(TODAY() >= M$1, N23, "") | ... NE23: =IF(TODAY() >= NE$1, NF23, "") -> 94 | NF23: {=XLOOKUP(A23, 'Books (2025)'!A23:A39, 'Books (2025)'!F23:F39)} -> 94
A24: What I Wish I Knew When I was 20 | B24: physical | C24: 202 | D24: =C24 - MAX($F24:NF24) -> 202 | F24: =IF(TODAY() >= F$1, G24, "") | G24: =IF(TODAY() >= G$1, H24, "") | H24: =IF(TODAY() >= H$1, I24, "") | I24: =IF(TODAY() >= I$1, J24, "") | J24: =IF(TODAY() >= J$1, K24, "") | K24: =IF(TODAY() >= K$1, L24, "") | L24: =IF(TODAY() >= L$1, M24, "") | M24: =IF(TODAY() >= M$1, N24, "") | ... NE24: =IF(TODAY() >= NE$1, NF24, "") -> 0 | NF24: {=XLOOKUP(A24, 'Books (2025)'!A24:A39, 'Books (2025)'!F24:F39)} -> 0
A25: Getting the Love You Want | B25: Nook | C25: 298 | D25: =C25 - MAX($F25:NF25) -> 163 | F25: =IF(TODAY() >= F$1, G25, "") | G25: =IF(TODAY() >= G$1, H25, "") | H25: =IF(TODAY() >= H$1, I25, "") | I25: =IF(TODAY() >= I$1, J25, "") | J25: =IF(TODAY() >= J$1, K25, "") | K25: =IF(TODAY() >= K$1, L25, "") | L25: =IF(TODAY() >= L$1, M25, "") | M25: =IF(TODAY() >= M$1, N25, "") | ... NE25: =IF(TODAY() >= NE$1, NF25, "") -> 135 | NF25: {=XLOOKUP(A25, 'Books (2025)'!A25:A39, 'Books (2025)'!F25:F39)} -> 135
A26: How to Do the Work | B26: Nook | C26: 274 | D26: =C26 - MAX($F26:NF26) -> 135 | F26: =IF(TODAY() >= F$1, G26, "") | G26: =IF(TODAY() >= G$1, H26, "") | H26: =IF(TODAY() >= H$1, I26, "") | I26: =IF(TODAY() >= I$1, J26, "") | J26: =IF(TODAY() >= J$1, K26, "") | K26: =IF(TODAY() >= K$1, L26, "") | L26: =IF(TODAY() >= L$1, M26, "") | M26: =IF(TODAY() >= M$1, N26, "") | ... NE26: =IF(TODAY() >= NE$1, NF26, "") -> 139 | NF26: {=XLOOKUP(A26, 'Books (2025)'!A26:A39, 'Books (2025)'!F26:F39)} -> 139
A27: The Seven Principles for Making Marriage Work | B27: Nook | C27: 272 | D27: =C27 - MAX($F27:NF27) -> 123 | F27: =IF(TODAY() >= F$1, G27, "") | G27: =IF(TODAY() >= G$1, H27, "") | H27: =IF(TODAY() >= H$1, I27, "") | I27: =IF(TODAY() >= I$1, J27, "") | J27: =IF(TODAY() >= J$1, K27, "") | K27: =IF(TODAY() >= K$1, L27, "") | L27: =IF(TODAY() >= L$1, M27, "") | M27: =IF(TODAY() >= M$1, N27, "") | ... NE27: =IF(TODAY() >= NE$1, NF27, "") -> 149 | NF27: {=XLOOKUP(A27, 'Books (2025)'!A27:A39, 'Books (2025)'!F27:F39)} -> 149
A28: The DBT Workbook for Narcissistic Abuse and Gaslighting | B28: Nook | C28: 95 | D28: =C28 - MAX($F28:NF28) -> 95 | F28: =IF(TODAY() >= F$1, G28, "") | G28: =IF(TODAY() >= G$1, H28, "") | H28: =IF(TODAY() >= H$1, I28, "") | I28: =IF(TODAY() >= I$1, J28, "") | J28: =IF(TODAY() >= J$1, K28, "") | K28: =IF(TODAY() >= K$1, L28, "") | L28: =IF(TODAY() >= L$1, M28, "") | M28: =IF(TODAY() >= M$1, N28, "") | ... NE28: =IF(TODAY() >= NE$1, NF28, "") -> 0 | NF28: {=XLOOKUP(A28, 'Books (2025)'!A28:A39, 'Books (2025)'!F28:F39)} -> 0
A29: How to Be the Love You Seek | B29: Nook | C29: 261 | D29: =C29 - MAX($F29:NF29) -> 86 | F29: =IF(TODAY() >= F$1, G29, "") | G29: =IF(TODAY() >= G$1, H29, "") | H29: =IF(TODAY() >= H$1, I29, "") | I29: =IF(TODAY() >= I$1, J29, "") | J29: =IF(TODAY() >= J$1, K29, "") | K29: =IF(TODAY() >= K$1, L29, "") | L29: =IF(TODAY() >= L$1, M29, "") | M29: =IF(TODAY() >= M$1, N29, "") | ... NE29: =IF(TODAY() >= NE$1, NF29, "") -> 175 | NF29: {=XLOOKUP(A29, 'Books (2025)'!A29:A39, 'Books (2025)'!F29:F39)} -> 175
A30: Your Somatic Therapy Toolbox | B30: Kindle | C30: 153 | D30: =C30 - MAX($F30:NF30) -> 153 | F30: =IF(TODAY() >= F$1, G30, "") | G30: =IF(TODAY() >= G$1, H30, "") | H30: =IF(TODAY() >= H$1, I30, "") | I30: =IF(TODAY() >= I$1, J30, "") | J30: =IF(TODAY() >= J$1, K30, "") | K30: =IF(TODAY() >= K$1, L30, "") | L30: =IF(TODAY() >= L$1, M30, "") | M30: =IF(TODAY() >= M$1, N30, "") | ... NE30: =IF(TODAY() >= NE$1, NF30, "") -> 0 | NF30: {=XLOOKUP(A30, 'Books (2025)'!A30:A39, 'Books (2025)'!F30:F39)} -> 0
A31: Notes on Being a Man | B31: Nook | C31: 282 | D31: =C31 - MAX($F31:NF31) -> 159 | F31: =IF(TODAY() >= F$1, G31, "") | G31: =IF(TODAY() >= G$1, H31, "") | H31: =IF(TODAY() >= H$1, I31, "") | I31: =IF(TODAY() >= I$1, J31, "") | J31: =IF(TODAY() >= J$1, K31, "") | K31: =IF(TODAY() >= K$1, L31, "") | L31: =IF(TODAY() >= L$1, M31, "") | M31: =IF(TODAY() >= M$1, N31, "") | ... NE31: =IF(TODAY() >= NE$1, NF31, "") -> 123 | NF31: {=XLOOKUP(A31, 'Books (2025)'!A31:A39, 'Books (2025)'!F31:F39)} -> 123
A32: Scattered Minds
A33: Taking Charge of Adult ADHD
A34: The Gift of Imperfection, Brene Brown
A35: Everything is Tuberculosis, John Greene
A36: Cues: Master the Secret Language of Charismatic Communication
F37: =IF(TODAY() >= F$1, G37, "") | G37: =IF(TODAY() >= G$1, H37, "") | H37: =IF(TODAY() >= H$1, I37, "") | I37: =IF(TODAY() >= I$1, J37, "") | J37: =IF(TODAY() >= J$1, K37, "") | K37: =IF(TODAY() >= K$1, L37, "") | L37: =IF(TODAY() >= L$1, M37, "") | M37: =IF(TODAY() >= M$1, N37, "") | ... DX37: =IF(TODAY() >= DX$1, DY37, "")
A38: metadata
A39: daily reading goal (pages) | B39: 15

Sheet Books (2025)
A1: Title | B1: Format | C1: Pages | D1: Remain | E1: Active | F1: =G1+1 -> 46022 | G1: =H1+1 -> 46021 | H1: =I1+1 -> 46020 | I1: =J1+1 -> 46019 | J1: =K1+1 -> 46018 | K1: =L1+1 -> 46017 | L1: =M1+1 -> 46016 | M1: =N1+1 -> 46015 | ... MV1: =MW1+1 -> 45668 | MW1: 45667
A2: books finished YTD | F2: {=IF(TODAY() >= F$1, SUM(N($C6:$C52=F6:F52)), "")} -> 21 | G2: {=IF(TODAY() >= G$1, SUM(N($C6:$C52=G6:G52)), "")} -> 21 | H2: {=IF(TODAY() >= H$1, SUM(N($C6:$C52=H6:H52)), "")} -> 21 | I2: {=IF(TODAY() >= I$1, SUM(N($C6:$C52=I6:I52)), "")} -> 21 | J2: {=IF(TODAY() >= J$1, SUM(N($C6:$C52=J6:J52)), "")} -> 21 | K2: {=IF(TODAY() >= K$1, SUM(N($C6:$C52=K6:K52)), "")} -> 21 | L2: {=IF(TODAY() >= L$1, SUM(N($C6:$C52=L6:L52)), "")} -> 21 | M2: {=IF(TODAY() >= M$1, SUM(N($C6:$C52=M6:M52)), "")} -> 21 | ... MW2: {=IF(TODAY() >= MW$1, SUM(N($C6:$C52=MW6:MW52)), "")} -> 3
A3: pages read today | F3: =IF(TODAY() >= F$1, SUMIFS(F6:F52, $C6:$C52, "<>") - SUMIFS(G6:G52, $C6:$C52, "<>"), "") -> 0 | G3: =IF(TODAY() >= G$1, SUMIFS(G6:G52, $C6:$C52, "<>") - SUMIFS(H6:H52, $C6:$C52, "<>"), "") -> 0 | H3: =IF(TODAY() >= H$1, SUMIFS(H6:H52, $C6:$C52, "<>") - SUMIFS(I6:I52, $C6:$C52, "<>"), "") -> 123 | I3: =IF(TODAY() >= I$1, SUMIFS(I6:I52, $C6:$C52, "<>") - SUMIFS(J6:J52, $C6:$C52, "<>"), "") -> 0 | J3: =IF(TODAY() >= J$1, SUMIFS(J6:J52, $C6:$C52, "<>") - SUMIFS(K6:K52, $C6:$C52, "<>"), "") -> 0 | K3: =IF(TODAY() >= K$1, SUMIFS(K6:K52, $C6:$C52, "<>") - SUMIFS(L6:L52, $C6:$C52, "<>"), "") -> 0 | L3: =IF(TODAY() >= L$1, SUMIFS(L6:L52, $C6:$C52, "<>") - SUMIFS(M6:M52, $C6:$C52, "<>"), "") -> 0 | M3: =IF(TODAY() >= M$1, SUMIFS(M6:M52, $C6:$C52, "<>") - SUMIFS(N6:N52, $C6:$C52, "<>"), "") -> 0 | ... MV3: =IF(TODAY() >= MV$1, SUMIFS(MV6:MV52, $C6:$C52, "<>") - SUMIFS(MW6:MW52, $C6:$C52, "<>"), "") -> 0 | MW3: 0
A4: monthly pages read cumulative | F4: =G4+F3 -> 5364.029 | G4: =H4+G3 -> 5364.029 | H4: =I4+H3 -> 5364.029 | I4: =J4+I3 -> 5241.029 | J4: =K4+J3 -> 5241.029 | K4: =L4+K3 -> 5241.029 | L4: =M4+L3 -> 5241.029 | M4: =N4+M3 -> 5241.029 | ... MV4: =MW4+MV3 -> 0 | MW4: =IF(TODAY() >= MW$1, SUMIFS(MW3, MW1, ">="&DATE(YEAR(MW1), MONTH(MW1), 1)), "") -> 0
A5: monthly goal | F5: =IF(TODAY() >= F1, (date(YEAR(F$1),MONTH(F$1)+1,1) - date(YEAR(F$1),MONTH(F$1),1)) * $B$52, "") -> 465 | G5: =IF(TODAY() >= G1, (date(YEAR(G$1),MONTH(G$1)+1,1) - date(YEAR(G$1),MONTH(G$1),1)) * $B$52, "") -> 465 | H5: =IF(TODAY() >= H1, (date(YEAR(H$1),MONTH(H$1)+1,1) - date(YEAR(H$1),MONTH(H$1),1)) * $B$52, "") -> 465 | I5: =IF(TODAY() >= I1, (date(YEAR(I$1),MONTH(I$1)+1,1) - date(YEAR(I$1),MONTH(I$1),1)) * $B$52, "") -> 465 | J5: =IF(TODAY() >= J1, (date(YEAR(J$1),MONTH(J$1)+1,1) - date(YEAR(J$1),MONTH(J$1),1)) * $B$52, "") -> 465 | K5: =IF(TODAY() >= K1, (date(YEAR(K$1),MONTH(K$1)+1,1) - date(YEAR(K$1),MONTH(K$1),1)) * $B$52, "") -> 465 | L5: =IF(TODAY() >= L1, (date(YEAR(L$1),MONTH(L$1)+1,1) - date(YEAR(L$1),MONTH(L$1),1)) * $B$52, "") -> 465 | M5: =IF(TODAY() >= M1, (date(YEAR(M$1),MONTH(M$1)+1,1) - date(YEAR(M$1),MONTH(M$1),1)) * $B$52, "") -> 465 | ... MW5: =IF(TODAY() >= MW1, (date(YEAR(MW$1),MONTH(MW$1)+1,1) - date(YEAR(MW$1),MONTH(MW$1),1)) * $B$52, "") -> 465
A6: The Happiness Trap | B6: Kindle | C6: 293 | D6: =C6 - MAX($F6:MW6) -> 222 | E6: Y | F6: =IF(TODAY() >= F$1, G6, "") -> 71 | G6: =IF(TODAY() >= G$1, H6, "") -> 71 | H6: =IF(TODAY() >= H$1, I6, "") -> 71 | I6: =IF(TODAY() >= I$1, J6, "") -> 71 | J6: =IF(TODAY() >= J$1, K6, "") -> 71 | K6: =IF(TODAY() >= K$1, L6, "") -> 71 | L6: =IF(TODAY() >= L$1, M6, "") -> 71 | M6: =IF(TODAY() >= M$1, N6, "") -> 71 | ... DO6: =IF(TODAY() >= DO$1, DP6, "") -> 71 | DP6: 71 | DQ6: =IF(TODAY() >= DQ$1, DR6, "") -> 62 | DR6: =IF(TODAY() >= DR$1, DS6, "") -> 62 | DS6: =IF(TODAY() >= DS$1, DT6, "") -> 62 | DT6: =IF(TODAY() >= DT$1, DU6, "") -> 62 | DU6: =IF(TODAY() >= DU$1, DV6, "") -> 62 | DV6: =IF(TODAY() >= DV$1, DW6, "") -> 62 | DW6: =IF(TODAY() >= DW$1, DX6, "") -> 62 | DX6: =IF(TODAY() >= DX$1, DY6, "") -> 62 | ... GF6: =IF(TODAY() >= GF$1, GG6, "") -> 62 | GG6: =IF(TODAY() >= GG$1, HL6, "") -> 62 | GH6: =IF(TODAY() >= GH$1, GI6, "") -> 62 | GI6: =IF(TODAY() >= GI$1, GJ6, "") -> 62 | GJ6: =IF(TODAY() >= GJ$1, GK6, "") -> 62 | GK6: =IF(TODAY() >= GK$1, GL6, "") -> 62 | GL6: =IF(TODAY() >= GL$1, GM6, "") -> 62 | GM6: =IF(TODAY() >= GM$1, GN6, "") -> 62 | GN6: =IF(TODAY() >= GN$1, GO6, "") -> 62 | GO6: =IF(TODAY() >= GO$1, GP6, "") -> 62 | ... MD6: =IF(TODAY() >= MD$1, ME6, "") -> 62 | ME6: =MF6 -> 62 | MF6: =MG6 -> 62 | MG6: =MH6 -> 62 | MH6: =MI6 -> 62 | MI6: =MJ6 -> 62 | MJ6: =MK6 -> 62 | MK6: =ML6 -> 62 | ML6: =MM6 -> 62 | ... MU6: =MV6 -> 62 | MV6: 62 | MW6: 62
A7: Getting Past Your Past | B7: Libby | C7: 352 | D7: =C7 - MAX($F7:MW7) -> 330.97101 | E7: Y | F7: =IF(TODAY() >= F$1, G7, "") -> 21.028994 | G7: =IF(TODAY() >= G$1, H7, "") -> 21.028994 | H7: =IF(TODAY() >= H$1, I7, "") -> 21.028994 | I7: =IF(TODAY() >= I$1, J7, "") -> 21.028994 | J7: =IF(TODAY() >= J$1, K7, "") -> 21.028994 | K7: =IF(TODAY() >= K$1, L7, "") -> 21.028994 | L7: =IF(TODAY() >= L$1, M7, "") -> 21.028994 | M7: =IF(TODAY() >= M$1, N7, "") -> 21.028994 | ... EU7: =IF(TODAY() >= EU$1, EV7, "") -> 21.028994 | EV7: =(43+8/60)/(12*60+2)*$C7 -> 21.028994 | EW7: =IF(TODAY() >= EW$1, EX7, "") -> 0 | EX7: =IF(TODAY() >= EX$1, EY7, "") -> 0 | EY7: =IF(TODAY() >= EY$1, EZ7, "") -> 0 | EZ7: =IF(TODAY() >= EZ$1, FA7, "") -> 0 | FA7: =IF(TODAY() >= FA$1, FB7, "") -> 0 | FB7: =IF(TODAY() >= FB$1, FC7, "") -> 0 | FC7: =IF(TODAY() >= FC$1, FD7, "") -> 0 | FD7: =IF(TODAY() >= FD$1, FE7, "") -> 0 | ... GF7: =IF(TODAY() >= GF$1, GG7, "") -> 0 | GG7: 0 | GH7: =IF(TODAY() >= GH$1, GI7, "") | GI7: =IF(TODAY() >= GI$1, GJ7, "") | GJ7: =IF(TODAY() >= GJ$1, GK7, "") | GK7: =IF(TODAY() >= GK$1, GL7, "") | GL7: =IF(TODAY() >= GL$1, GM7, "") | GM7: =IF(TODAY() >= GM$1, GN7, "") | GN7: =IF(TODAY() >= GN$1, GO7, "") | GO7: =IF(TODAY() >= GO$1, GP7, "") | ... HK7: =IF(TODAY() >= HK$1, HL7, "")
A8: How to Avoid H.E.N.R.Y Syndrome | B8: Kindle | C8: 218 | D8: =C8 - MAX($F8:MW8) -> 0 | F8: =IF(TODAY() >= F$1, G8, "") -> 218 | G8: =IF(TODAY() >= G$1, H8, "") -> 218 | H8: =IF(TODAY() >= H$1, I8, "") -> 218 | I8: =IF(TODAY() >= I$1, J8, "") -> 218 | J8: =IF(TODAY() >= J$1, K8, "") -> 218 | K8: =IF(TODAY() >= K$1, L8, "") -> 218 | L8: =IF(TODAY() >= L$1, M8, "") -> 218 | M8: =IF(TODAY() >= M$1, N8, "") -> 218 | ... DZ8: =IF(TODAY() >= DZ$1, EA8, "") -> 218 | EA8: =ROUND(2007/2007*218,0) -> 218 | EB8: =IF(TODAY() >= EB$1, EC8, "") -> 105 | EC8: =IF(TODAY() >= EC$1, ED8, "") -> 105 | ED8: =IF(TODAY() >= ED$1, EE8, "") -> 105 | EE8: =IF(TODAY() >= EE$1, EF8, "") -> 105 | EF8: =IF(TODAY() >= EF$1, EG8, "") -> 105 | EG8: =IF(TODAY() >= EG$1, EH8, "") -> 105 | EH8: =IF(TODAY() >= EH$1, EI8, "") -> 105 | EI8: =IF(TODAY() >= EI$1, EJ8, "") -> 105 | EJ8: =ROUND(970/2007*218,0) -> 105 | EK8: =IF(TODAY() >= EK$1, EL8, "") -> 71 | EL8: =IF(TODAY() >= EL$1, EM8, "") -> 71 | EM8: =IF(TODAY() >= EM$1, EN8, "") -> 71 | EN8: =IF(TODAY() >= EN$1, EO8, "") -> 71 | EO8: =IF(TODAY() >= EO$1, EP8, "") -> 71 | EP8: =IF(TODAY() >= EP$1, EQ8, "") -> 71 | EQ8: =IF(TODAY() >= EQ$1, ER8, "") -> 71 | ER8: =IF(TODAY() >= ER$1, ES8, "") -> 71 | ... GF8: =IF(TODAY() >= GF$1, GG8, "") -> 71 | GG8: =IF(TODAY() >= GG$1, HL8, "") -> 71 | GH8: =IF(TODAY() >= GH$1, GI8, "") -> 71 | GI8: =IF(TODAY() >= GI$1, GJ8, "") -> 71 | GJ8: =IF(TODAY() >= GJ$1, GK8, "") -> 71 | GK8: =IF(TODAY() >= GK$1, GL8, "") -> 71 | GL8: =IF(TODAY() >= GL$1, GM8, "") -> 71 | GM8: =IF(TODAY() >= GM$1, GN8, "") -> 71 | GN8: =IF(TODAY() >= GN$1, GO8, "") -> 71 | GO8: =IF(TODAY() >= GO$1, GP8, "") -> 71 | ... LG8: =IF(TODAY() >= LG$1, LH8, "") -> 71 | LH8: =ROUND(653/2007*218,0) -> 71 | LI8: =IF(TODAY() >= LI$1, LJ8, "") -> 48 | LJ8: =IF(TODAY() >= LJ$1, LK8, "") -> 48 | LK8: =IF(TODAY() >= LK$1, LL8, "") -> 48 | LL8: =IF(TODAY() >= LL$1, LM8, "") -> 48 | LM8: =IF(TODAY() >= LM$1, LN8, "") -> 48 | LN8: =IF(TODAY() >= LN$1, LO8, "") -> 48 | LO8: =IF(TODAY() >= LO$1, LP8, "") -> 48 | LP8: =IF(TODAY() >= LP$1, LQ8, "") -> 48 | ... LZ8: =IF(TODAY() >= LZ$1, MA8, "") -> 48 | MA8: =ROUND(438/2007*218,0) -> 48 | MB8: =IF(TODAY() >= MB$1, MC8, "") -> 31 | MC8: =ROUND(282/2007*218,0) -> 31 | MD8: =IF(TODAY() >= MD$1, ME8, "") -> 0 | ME8: =MF8 -> 0 | MF8: =MG8 -> 0 | MG8: =MH8 -> 0 | MH8: =MI8 -> 0 | MI8: =MJ8 -> 0 | MJ8: =MK8 -> 0 | MK8: =ML8 -> 0 | ML8: =MM8 -> 0 | ... MU8: =MV8 -> 0 | MV8: 0 | MW8: 0
A9: The Book of Why | B9: Kindle | C9: 419 | D9: =C9 - MAX($F9:MW9) -> 419 | F9: =IF(TODAY() >= F$1, G9, "") -> 0 | G9: =IF(TODAY() >= G$1, H9, "") -> 0 | H9: =IF(TODAY() >= H$1, I9, "") -> 0 | I9: =IF(TODAY() >= I$1, J9, "") -> 0 | J9: =IF(TODAY() >= J$1, K9, "") -> 0 | K9: =IF(TODAY() >= K$1, L9, "") -> 0 | L9: =IF(TODAY() >= L$1, M9, "") -> 0 | M9: =IF(TODAY() >= M$1, N9, "") -> 0 | ... GF9: =IF(TODAY() >= GF$1, GG9, "") -> 0 | GG9: =IF(TODAY() >= GG$1, HL9, "") -> 0 | GH9: =IF(TODAY() >= GH$1, GI9, "") -> 0 | GI9: =IF(TODAY() >= GI$1, GJ9, "") -> 0 | GJ9: =IF(TODAY() >= GJ$1, GK9, "") -> 0 | GK9: =IF(TODAY() >= GK$1, GL9, "") -> 0 | GL9: =IF(TODAY() >= GL$1, GM9, "") -> 0 | GM9: =IF(TODAY() >= GM$1, GN9, "") -> 0 | GN9: =IF(TODAY() >= GN$1, GO9, "") -> 0 | GO9: =IF(TODAY() >= GO$1, GP9, "") -> 0 | ... MD9: =IF(TODAY() >= MD$1, ME9, "") -> 0 | ME9: =MF9 -> 0 | MF9: =MG9 -> 0 | MG9: =MH9 -> 0 | MH9: =MI9 -> 0 | MI9: =MJ9 -> 0 | MJ9: =MK9 -> 0 | MK9: =ML9 -> 0 | ML9: =MM9 -> 0 | ... MU9: =MV9 -> 0 | MV9: 0 | MW9: 0
A10: Validation | C10: 414 | D10: =C10 - MAX($F10:MW10) -> 414 | F10: =IF(TODAY() >= F$1, G10, "") -> 0 | G10: =IF(TODAY() >= G$1, H10, "") -> 0 | H10: =IF(TODAY() >= H$1, I10, "") -> 0 | I10: =IF(TODAY() >= I$1, J10, "") -> 0 | J10: =IF(TODAY() >= J$1, K10, "") -> 0 | K10: =IF(TODAY() >= K$1, L10, "") -> 0 | L10: =IF(TODAY() >= L$1, M10, "") -> 0 | M10: =IF(TODAY() >= M$1, N10, "") -> 0 | ... GF10: =IF(TODAY() >= GF$1, GG10, "") -> 0 | GG10: 0 | GH10: =IF(TODAY() >= GH$1, GI10, "") | GI10: =IF(TODAY() >= GI$1, GJ10, "") | GJ10: =IF(TODAY() >= GJ$1, GK10, "") | GK10: =IF(TODAY() >= GK$1, GL10, "") | GL10: =IF(TODAY() >= GL$1, GM10, "") | GM10: =IF(TODAY() >= GM$1, GN10, "") | GN10: =IF(TODAY() >= GN$1, GO10, "") | GO10: =IF(TODAY() >= GO$1, GP10, "") | ... HK10: =IF(TODAY() >= HK$1, HL10, "")
A11: The Real Happy Pill | C11: 414 | D11: =C11 - MAX($F11:MW11) -> 414 | F11: =IF(TODAY() >= F$1, G11, "") -> 0 | G11: =IF(TODAY() >= G$1, H11, "") -> 0 | H11: =IF(TODAY() >= H$1, I11, "") -> 0 | I11: =IF(TODAY() >= I$1, J11, "") -> 0 | J11: =IF(TODAY() >= J$1, K11, "") -> 0 | K11: =IF(TODAY() >= K$1, L11, "") -> 0 | L11: =IF(TODAY() >= L$1, M11, "") -> 0 | M11: =IF(TODAY() >= M$1, N11, "") -> 0 | ... GF11: =IF(TODAY() >= GF$1, GG11, "") -> 0 | GG11: =IF(TODAY() >= GG$1, HL11, "") -> 0 | GH11: =IF(TODAY() >= GH$1, GI11, "") -> 0 | GI11: =IF(TODAY() >= GI$1, GJ11, "") -> 0 | GJ11: =IF(TODAY() >= GJ$1, GK11, "") -> 0 | GK11: =IF(TODAY() >= GK$1, GL11, "") -> 0 | GL11: =IF(TODAY() >= GL$1, GM11, "") -> 0 | GM11: =IF(TODAY() >= GM$1, GN11, "") -> 0 | GN11: =IF(TODAY() >= GN$1, GO11, "") -> 0 | GO11: =IF(TODAY() >= GO$1, GP11, "") -> 0 | ... MD11: =IF(TODAY() >= MD$1, ME11, "") -> 0 | ME11: =MF11 -> 0 | MF11: =MG11 -> 0 | MG11: =MH11 -> 0 | MH11: =MI11 -> 0 | MI11: =MJ11 -> 0 | MJ11: =MK11 -> 0 | MK11: =ML11 -> 0 | ML11: =MM11 -> 0 | ... MU11: =MV11 -> 0 | MV11: 0 | MW11: 0
A12: The Body Keeps the Score | B12: Nook | C12: 414 | D12: =C12 - MAX($F12:MW12) -> 414 | F12: =IF(TODAY() >= F$1, G12, "") -> 0 | G12: =IF(TODAY() >= G$1, H12, "") -> 0 | H12: =IF(TODAY() >= H$1, I12, "") -> 0 | I12: =IF(TODAY() >= I$1, J12, "") -> 0 | J12: =IF(TODAY() >= J$1, K12, "") -> 0 | K12: =IF(TODAY() >= K$1, L12, "") -> 0 | L12: =IF(TODAY() >= L$1, M12, "") -> 0 | M12: =IF(TODAY() >= M$1, N12, "") -> 0 | ... GF12: =IF(TODAY() >= GF$1, GG12, "") -> 0 | GG12: =IF(TODAY() >= GG$1, HL12, "") -> 0 | GH12: =IF(TODAY() >= GH$1, GI12, "") -> 0 | GI12: =IF(TODAY() >= GI$1, GJ12, "") -> 0 | GJ12: =IF(TODAY() >= GJ$1, GK12, "") -> 0 | GK12: =IF(TODAY() >= GK$1, GL12, "") -> 0 | GL12: =IF(TODAY() >= GL$1, GM12, "") -> 0 | GM12: =IF(TODAY() >= GM$1, GN12, "") -> 0 | GN12: =IF(TODAY() >= GN$1, GO12, "") -> 0 | GO12: =IF(TODAY() >= GO$1, GP12, "") -> 0 | ... MD12: =IF(TODAY() >= MD$1, ME12, "") -> 0 | ME12: =MF12 -> 0 | MF12: =MG12 -> 0 | MG12: =MH12 -> 0 | MH12: =MI12 -> 0 | MI12: =MJ12 -> 0 | MJ12: =MK12 -> 0 | MK12: =ML12 -> 0 | ML12: =MM12 -> 0 | ... MU12: =MV12 -> 0 | MV12: 0 | MW12: 0
A13: Tapping In | C13: 414 | D13: =C13 - MAX($F13:MW13) -> 414 | F13: =IF(TODAY() >= F$1, G13, "") -> 0 | G13: =IF(TODAY() >= G$1, H13, "") -> 0 | H13: =IF(TODAY() >= H$1, I13, "") -> 0 | I13: =IF(TODAY() >= I$1, J13, "") -> 0 | J13: =IF(TODAY() >= J$1, K13, "") -> 0 | K13: =IF(TODAY() >= K$1, L13, "") -> 0 | L13: =IF(TODAY() >= L$1, M13, "") -> 0 | M13: =IF(TODAY() >= M$1, N13, "") -> 0 | ... GF13: =IF(TODAY() >= GF$1, GG13, "") -> 0 | GG13: 0 | GH13: =IF(TODAY() >= GH$1, GI13, "") | GI13: =IF(TODAY() >= GI$1, GJ13, "") | GJ13: =IF(TODAY() >= GJ$1, GK13, "") | GK13: =IF(TODAY() >= GK$1, GL13, "") | GL13: =IF(TODAY() >= GL$1, GM13, "") | GM13: =IF(TODAY() >= GM$1, GN13, "") | GN13: =IF(TODAY() >= GN$1, GO13, "") | GO13: =IF(TODAY() >= GO$1, GP13, "") | ... HK13: =IF(TODAY() >= HK$1, HL13, "")
A14: Mrs. Dalloway | C14: 414 | D14: =C14 - MAX($F14:MW14) -> 414 | F14: =IF(TODAY() >= F$1, G14, "") -> 0 | G14: =IF(TODAY() >= G$1, H14, "") -> 0 | H14: =IF(TODAY() >= H$1, I14, "") -> 0 | I14: =IF(TODAY() >= I$1, J14, "") -> 0 | J14: =IF(TODAY() >= J$1, K14, "") -> 0 | K14: =IF(TODAY() >= K$1, L14, "") -> 0 | L14: =IF(TODAY() >= L$1, M14, "") -> 0 | M14: =IF(TODAY() >= M$1, N14, "") -> 0 | ... GF14: =IF(TODAY() >= GF$1, GG14, "") -> 0 | GG14: 0 | GH14: =IF(TODAY() >= GH$1, GI14, "") | GI14: =IF(TODAY() >= GI$1, GJ14, "") | GJ14: =IF(TODAY() >= GJ$1, GK14, "") | GK14: =IF(TODAY() >= GK$1, GL14, "") | GL14: =IF(TODAY() >= GL$1, GM14, "") | GM14: =IF(TODAY() >= GM$1, GN14, "") | GN14: =IF(TODAY() >= GN$1, GO14, "") | GO14: =IF(TODAY() >= GO$1, GP14, "") | ... HK14: =IF(TODAY() >= HK$1, HL14, "")
A15: Hold Me Tight | B15: Libby | C15: 414 | D15: =C15 - MAX($F15:MW15) -> 414 | F15: =IF(TODAY() >= F$1, G15, "") -> 0 | G15: =IF(TODAY() >= G$1, H15, "") -> 0 | H15: =IF(TODAY() >= H$1, I15, "") -> 0 | I15: =IF(TODAY() >= I$1, J15, "") -> 0 | J15: =IF(TODAY() >= J$1, K15, "") -> 0 | K15: =IF(TODAY() >= K$1, L15, "") -> 0 | L15: =IF(TODAY() >= L$1, M15, "") -> 0 | M15: =IF(TODAY() >= M$1, N15, "") -> 0 | ... GF15: =IF(TODAY() >= GF$1, GG15, "") -> 0 | GG15: 0 | GH15: =IF(TODAY() >= GH$1, GI15, "") | GI15: =IF(TODAY() >= GI$1, GJ15, "") | GJ15: =IF(TODAY() >= GJ$1, GK15, "") | GK15: =IF(TODAY() >= GK$1, GL15, "") | GL15: =IF(TODAY() >= GL$1, GM15, "") | GM15: =IF(TODAY() >= GM$1, GN15, "") | GN15: =IF(TODAY() >= GN$1, GO15, "") | GO15: =IF(TODAY() >= GO$1, GP15, "") | ... HK15: =IF(TODAY() >= HK$1, HL15, "")
A16: DBT Workbook for Narcissistic Abuse & Gaslighting | B16: Nook | C16: 414 | D16: =C16 - MAX($F16:MW16) -> 414 | F16: =IF(TODAY() >= F$1, G16, "") -> 0 | G16: =IF(TODAY() >= G$1, H16, "") -> 0 | H16: =IF(TODAY() >= H$1, I16, "") -> 0 | I16: =IF(TODAY() >= I$1, J16, "") -> 0 | J16: =IF(TODAY() >= J$1, K16, "") -> 0 | K16: =IF(TODAY() >= K$1, L16, "") -> 0 | L16: =IF(TODAY() >= L$1, M16, "") -> 0 | M16: =IF(TODAY() >= M$1, N16, "") -> 0 | ... GF16: =IF(TODAY() >= GF$1, GG16, "") -> 0 | GG16: =IF(TODAY() >= GG$1, HL16, "") -> 0 | GH16: =IF(TODAY() >= GH$1, GI16, "") -> 0 | GI16: =IF(TODAY() >= GI$1, GJ16, "") -> 0 | GJ16: =IF(TODAY() >= GJ$1, GK16, "") -> 0 | GK16: =IF(TODAY() >= GK$1, GL16, "") -> 0 | GL16: =IF(TODAY() >= GL$1, GM16, "") -> 0 | GM16: =IF(TODAY() >= GM$1, GN16, "") -> 0 | GN16: =IF(TODAY() >= GN$1, GO16, "") -> 0 | GO16: =IF(TODAY() >= GO$1, GP16, "") -> 0 | ... MD16: =IF(TODAY() >= MD$1, ME16, "") -> 0 | ME16: =MF16 -> 0 | MF16: =MG16 -> 0 | MG16: =MH16 -> 0 | MH16: =MI16 -> 0 | MI16: =MJ16 -> 0 | MJ16: =MK16 -> 0 | MK16: =ML16 -> 0 | ML16: =MM16 -> 0 | ... MU16: =MV16 -> 0 | MV16: 0 | MW16: 0
A17: CPTSD Workbook | B17: Kindle | C17: 414 | D17: =C17 - MAX($F17:MW17) -> 414 | F17: =IF(TODAY() >= F$1, G17, "") -> 0 | G17: =IF(TODAY() >= G$1, H17, "") -> 0 | H17: =IF(TODAY() >= H$1, I17, "") -> 0 | I17: =IF(TODAY() >= I$1, J17, "") -> 0 | J17: =IF(TODAY() >= J$1, K17, "") -> 0 | K17: =IF(TODAY() >= K$1, L17, "") -> 0 | L17: =IF(TODAY() >= L$1, M17, "") -> 0 | M17: =IF(TODAY() >= M$1, N17, "") -> 0 | ... GF17: =IF(TODAY() >= GF$1, GG17, "") -> 0 | GG17: =IF(TODAY() >= GG$1, HL17, "") -> 0 | GH17: =IF(TODAY() >= GH$1, GI17, "") -> 0 | GI17: =IF(TODAY() >= GI$1, GJ17, "") -> 0 | GJ17: =IF(TODAY() >= GJ$1, GK17, "") -> 0 | GK17: =IF(TODAY() >= GK$1, GL17, "") -> 0 | GL17: =IF(TODAY() >= GL$1, GM17, "") -> 0 | GM17: =IF(TODAY() >= GM$1, GN17, "") -> 0 | GN17: =IF(TODAY() >= GN$1, GO17, "") -> 0 | GO17: =IF(TODAY() >= GO$1, GP17, "") -> 0 | ... MD17: =IF(TODAY() >= MD$1, ME17, "") -> 0 | ME17: =MF17 -> 0 | MF17: =MG17 -> 0 | MG17: =MH17 -> 0 | MH17: =MI17 -> 0 | MI17: =MJ17 -> 0 | MJ17: =MK17 -> 0 | MK17: =ML17 -> 0 | ML17: =MM17 -> 0 | ... MU17: =MV17 -> 0 | MV17: 0 | MW17: 0
A18: It's Not You | B18: Libby | C18: 368 | D18: =C18 - MAX($F18:MW18) -> 368 | F18: =IF(TODAY() >= F$1, G18, "") -> 0 | G18: =IF(TODAY() >= G$1, H18, "") -> 0 | H18: =IF(TODAY() >= H$1, I18, "") -> 0 | I18: =IF(TODAY() >= I$1, J18, "") -> 0 | J18: =IF(TODAY() >= J$1, K18, "") -> 0 | K18: =IF(TODAY() >= K$1, L18, "") -> 0 | L18: =IF(TODAY() >= L$1, M18, "") -> 0 | M18: =IF(TODAY() >= M$1, N18, "") -> 0 | ... GF18: =IF(TODAY() >= GF$1, GG18, "") -> 0 | GG18: =IF(TODAY() >= GG$1, HL18, "") -> 0 | GH18: =IF(TODAY() >= GH$1, GI18, "") -> 0 | GI18: =IF(TODAY() >= GI$1, GJ18, "") -> 0 | GJ18: =IF(TODAY() >= GJ$1, GK18, "") -> 0 | GK18: =IF(TODAY() >= GK$1, GL18, "") -> 0 | GL18: =IF(TODAY() >= GL$1, GM18, "") -> 0 | GM18: =IF(TODAY() >= GM$1, GN18, "") -> 0 | GN18: =IF(TODAY() >= GN$1, GO18, "") -> 0 | GO18: =IF(TODAY() >= GO$1, GP18, "") -> 0 | ... MV18: =IF(TODAY() >= MV$1, MW18, "") -> 0 | MW18: 0
A19: Complex PTSD | B19: Kindle | C19: 341 | D19: =C19 - MAX($F19:MW19) -> 339 | F19: =IF(TODAY() >= F$1, G19, "") -> 2 | G19: =IF(TODAY() >= G$1, H19, "") -> 2 | H19: =IF(TODAY() >= H$1, I19, "") -> 2 | I19: =IF(TODAY() >= I$1, J19, "") -> 2 | J19: =IF(TODAY() >= J$1, K19, "") -> 2 | K19: =IF(TODAY() >= K$1, L19, "") -> 2 | L19: =IF(TODAY() >= L$1, M19, "") -> 2 | M19: =IF(TODAY() >= M$1, N19, "") -> 2 | ... GF19: =IF(TODAY() >= GF$1, GG19, "") -> 2 | GG19: =IF(TODAY() >= GG$1, HL19, "") -> 2 | GH19: =IF(TODAY() >= GH$1, GI19, "") -> 2 | GI19: =IF(TODAY() >= GI$1, GJ19, "") -> 2 | GJ19: =IF(TODAY() >= GJ$1, GK19, "") -> 2 | GK19: =IF(TODAY() >= GK$1, GL19, "") -> 2 | GL19: =IF(TODAY() >= GL$1, GM19, "") -> 2 | GM19: =IF(TODAY() >= GM$1, GN19, "") -> 2 | GN19: =IF(TODAY() >= GN$1, GO19, "") -> 2 | GO19: =IF(TODAY() >= GO$1, GP19, "") -> 2 | ... JI19: =IF(TODAY() >= JI$1, JJ19, "") -> 2 | JJ19: 2 | JK19: =IF(TODAY() >= JK$1, JL19, "") -> 2 | JL19: =IF(TODAY() >= JL$1, JM19, "") -> 2 | JM19: =IF(TODAY() >= JM$1, JN19, "") -> 2 | JN19: =IF(TODAY() >= JN$1, JO19, "") -> 2 | JO19: =IF(TODAY() >= JO$1, JP19, "") -> 2 | JP19: =IF(TODAY() >= JP$1, JQ19, "") -> 2 | JQ19: =IF(TODAY() >= JQ$1, JR19, "") -> 2 | JR19: =IF(TODAY() >= JR$1, JS19, "") -> 2 | ... KN19: =IF(TODAY() >= KN$1, KO19, "") -> 2 | KO19: 2 | KP19: =IF(TODAY() >= KP$1, KQ19, "") -> 0 | KQ19: =IF(TODAY() >= KQ$1, KR19, "") -> 0 | KR19: =IF(TODAY() >= KR$1, KS19, "") -> 0 | KS19: =IF(TODAY() >= KS$1, KT19, "") -> 0 | KT19: =IF(TODAY() >= KT$1, KU19, "") -> 0 | KU19: =IF(TODAY() >= KU$1, KV19, "") -> 0 | KV19: =IF(TODAY() >= KV$1, KW19, "") -> 0 | KW19: =IF(TODAY() >= KW$1, KX19, "") -> 0 | ... MD19: =IF(TODAY() >= MD$1, ME19, "") -> 0 | ME19: =MF19 -> 0 | MF19: =MG19 -> 0 | MG19: =MH19 -> 0 | MH19: =MI19 -> 0 | MI19: =MJ19 -> 0 | MJ19: =MK19 -> 0 | MK19: =ML19 -> 0 | ML19: =MM19 -> 0 | ... MU19: =MV19 -> 0 | MV19: 0 | MW19: 0
A20: The (Mis)behavior of Markets | B20: Nook | C20: 307 | D20: =C20 - MAX($F20:MW20) -> 307 | F20: =IF(TODAY() >= F$1, G20, "") -> 0 | G20: =IF(TODAY() >= G$1, H20, "") -> 0 | H20: =IF(TODAY() >= H$1, I20, "") -> 0 | I20: =IF(TODAY() >= I$1, J20, "") -> 0 | J20: =IF(TODAY() >= J$1, K20, "") -> 0 | K20: =IF(TODAY() >= K$1, L20, "") -> 0 | L20: =IF(TODAY() >= L$1, M20, "") -> 0 | M20: =IF(TODAY() >= M$1, N20, "") -> 0 | ... GF20: =IF(TODAY() >= GF$1, GG20, "") -> 0 | GG20: =IF(TODAY() >= GG$1, HL20, "") -> 0 | GH20: =IF(TODAY() >= GH$1, GI20, "") -> 0 | GI20: =IF(TODAY() >= GI$1, GJ20, "") -> 0 | GJ20: =IF(TODAY() >= GJ$1, GK20, "") -> 0 | GK20: =IF(TODAY() >= GK$1, GL20, "") -> 0 | GL20: =IF(TODAY() >= GL$1, GM20, "") -> 0 | GM20: =IF(TODAY() >= GM$1, GN20, "") -> 0 | GN20: =IF(TODAY() >= GN$1, GO20, "") -> 0 | GO20: =IF(TODAY() >= GO$1, GP20, "") -> 0 | ... MD20: =IF(TODAY() >= MD$1, ME20, "") -> 0 | ME20: =MF20 -> 0 | MF20: =MG20 -> 0 | MG20: =MH20 -> 0 | MH20: =MI20 -> 0 | MI20: =MJ20 -> 0 | MJ20: =MK20 -> 0 | MK20: =ML20 -> 0 | ML20: =MM20 -> 0 | ... MU20: =MV20 -> 0 | MV20: 0 | MW20: 0
A21: What My Bones Know | B21: Libby | C21: 352 | D21: =C21 - MAX($F21:MW21) -> 305 | F21: =IF(TODAY() >= F$1, G21, "") -> 47 | G21: =IF(TODAY() >= G$1, H21, "") -> 47 | H21: =IF(TODAY() >= H$1, I21, "") -> 47 | I21: =IF(TODAY() >= I$1, J21, "") -> 47 | J21: =IF(TODAY() >= J$1, K21, "") -> 47 | K21: =IF(TODAY() >= K$1, L21, "") -> 47 | L21: =IF(TODAY() >= L$1, M21, "") -> 47 | M21: =IF(TODAY() >= M$1, N21, "") -> 47 | ... GF21: =IF(TODAY() >= GF$1, GG21, "") -> 47 | GG21: =IF(TODAY() >= GG$1, HL21, "") -> 47 | GH21: =IF(TODAY() >= GH$1, GI21, "") -> 47 | GI21: =IF(TODAY() >= GI$1, GJ21, "") -> 47 | GJ21: =IF(TODAY() >= GJ$1, GK21, "") -> 47 | GK21: =IF(TODAY() >= GK$1, GL21, "") -> 47 | GL21: =IF(TODAY() >= GL$1, GM21, "") -> 47 | GM21: =IF(TODAY() >= GM$1, GN21, "") -> 47 | GN21: =IF(TODAY() >= GN$1, GO21, "") -> 47 | GO21: =IF(TODAY() >= GO$1, GP21, "") -> 47 | ... MD21: =IF(TODAY() >= MD$1, ME21, "") -> 47 | ME21: 47 | MF21: =MG21 -> 0 | MG21: =MH21 -> 0 | MH21: =MI21 -> 0 | MI21: =MJ21 -> 0 | MJ21: 0 | MK21: =ML21 -> 0 | ML21: =MM21 -> 0 | MM21: =MN21 -> 0 | MN21: =MO21 -> 0 | MO21: =MP21 -> 0 | MP21: =MQ21 -> 0 | MQ21: =MR21 -> 0 | MR21: =MS21 -> 0 | ... MU21: =MV21 -> 0 | MV21: 0 | MW21: 0
A22: The Manager's Path | B22: Kindle | C22: 219 | D22: =C22 - MAX($F22:MW22) -> 219 | F22: =IF(TODAY() >= F$1, G22, "") -> 0 | G22: =IF(TODAY() >= G$1, H22, "") -> 0 | H22: =IF(TODAY() >= H$1, I22, "") -> 0 | I22: =IF(TODAY() >= I$1, J22, "") -> 0 | J22: =IF(TODAY() >= J$1, K22, "") -> 0 | K22: =IF(TODAY() >= K$1, L22, "") -> 0 | L22: =IF(TODAY() >= L$1, M22, "") -> 0 | M22: =IF(TODAY() >= M$1, N22, "") -> 0 | ... GF22: =IF(TODAY() >= GF$1, GG22, "") -> 0 | GG22: =IF(TODAY() >= GG$1, HL22, "") -> 0 | GH22: =IF(TODAY() >= GH$1, GI22, "") -> 0 | GI22: =IF(TODAY() >= GI$1, GJ22, "") -> 0 | GJ22: =IF(TODAY() >= GJ$1, GK22, "") -> 0 | GK22: =IF(TODAY() >= GK$1, GL22, "") -> 0 | GL22: =IF(TODAY() >= GL$1, GM22, "") -> 0 | GM22: =IF(TODAY() >= GM$1, GN22, "") -> 0 | GN22: =IF(TODAY() >= GN$1, GO22, "") -> 0 | GO22: =IF(TODAY() >= GO$1, GP22, "") -> 0 | ... MD22: =IF(TODAY() >= MD$1, ME22, "") -> 0 | ME22: =MF22 -> 0 | MF22: =MG22 -> 0 | MG22: =MH22 -> 0 | MH22: =MI22 -> 0 | MI22: =MJ22 -> 0 | MJ22: =MK22 -> 0 | MK22: =ML22 -> 0 | ML22: =MM22 -> 0 | ... MU22: =MV22 -> 0 | MV22: 0 | MW22: 0
A23: High Output Management | B23: Nook | C23: 215 | D23: =C23 - MAX($F23:MW23) -> 215 | F23: =IF(TODAY() >= F$1, G23, "") -> 0 | G23: =IF(TODAY() >= G$1, H23, "") -> 0 | H23: =IF(TODAY() >= H$1, I23, "") -> 0 | I23: =IF(TODAY() >= I$1, J23, "") -> 0 | J23: =IF(TODAY() >= J$1, K23, "") -> 0 | K23: =IF(TODAY() >= K$1, L23, "") -> 0 | L23: =IF(TODAY() >= L$1, M23, "") -> 0 | M23: =IF(TODAY() >= M$1, N23, "") -> 0 | ... GF23: =IF(TODAY() >= GF$1, GG23, "") -> 0 | GG23: =IF(TODAY() >= GG$1, HL23, "") -> 0 | GH23: =IF(TODAY() >= GH$1, GI23, "") -> 0 | GI23: =IF(TODAY() >= GI$1, GJ23, "") -> 0 | GJ23: =IF(TODAY() >= GJ$1, GK23, "") -> 0 | GK23: =IF(TODAY() >= GK$1, GL23, "") -> 0 | GL23: =IF(TODAY() >= GL$1, GM23, "") -> 0 | GM23: =IF(TODAY() >= GM$1, GN23, "") -> 0 | GN23: =IF(TODAY() >= GN$1, GO23, "") -> 0 | GO23: =IF(TODAY() >= GO$1, GP23, "") -> 0 | ... MD23: =IF(TODAY() >= MD$1, ME23, "") -> 0 | ME23: =MF23 -> 0 | MF23: =MG23 -> 0 | MG23: =MH23 -> 0 | MH23: =MI23 -> 0 | MI23: =MJ23 -> 0 | MJ23: =MK23 -> 0 | MK23: =ML23 -> 0 | ML23: =MM23 -> 0 | ... MU23: =MV23 -> 0 | MV23: 0 | MW23: 0
A24: Measure What Matters | B24: Nook | C24: 298 | D24: =C24 - MAX($F24:MW24) -> 204 | F24: =IF(TODAY() >= F$1, G24, "") -> 94 | G24: =IF(TODAY() >= G$1, H24, "") -> 94 | H24: =IF(TODAY() >= H$1, I24, "") -> 94 | I24: =IF(TODAY() >= I$1, J24, "") -> 94 | J24: =IF(TODAY() >= J$1, K24, "") -> 94 | K24: =IF(TODAY() >= K$1, L24, "") -> 94 | L24: =IF(TODAY() >= L$1, M24, "") -> 94 | M24: =IF(TODAY() >= M$1, N24, "") -> 94 | ... GF24: =IF(TODAY() >= GF$1, GG24, "") -> 94 | GG24: =IF(TODAY() >= GG$1, HL24, "") -> 94 | GH24: =IF(TODAY() >= GH$1, GI24, "") -> 94 | GI24: =IF(TODAY() >= GI$1, GJ24, "") -> 94 | GJ24: =IF(TODAY() >= GJ$1, GK24, "") -> 94 | GK24: =IF(TODAY() >= GK$1, GL24, "") -> 94 | GL24: =IF(TODAY() >= GL$1, GM24, "") -> 94 | GM24: =IF(TODAY() >= GM$1, GN24, "") -> 94 | GN24: =IF(TODAY() >= GN$1, GO24, "") -> 94 | GO24: =IF(TODAY() >= GO$1, GP24, "") -> 94 | ... MD24: =IF(TODAY() >= MD$1, ME24, "") -> 94 | ME24: =MF24 -> 94 | MF24: =MG24 -> 94 | MG24: =MH24 -> 94 | MH24: =MI24 -> 94 | MI24: =MJ24 -> 94 | MJ24: =MK24 -> 94 | MK24: =ML24 -> 94 | ML24: =MM24 -> 94 | ... MU24: =MV24 -> 94 | MV24: 94 | MW24: 94
A25: What I Wish I Knew When I was 20 | B25: physical | C25: 202 | D25: =C25 - MAX($F25:MW25) -> 202 | F25: =IF(TODAY() >= F$1, G25, "") -> 0 | G25: =IF(TODAY() >= G$1, H25, "") -> 0 | H25: =IF(TODAY() >= H$1, I25, "") -> 0 | I25: =IF(TODAY() >= I$1, J25, "") -> 0 | J25: =IF(TODAY() >= J$1, K25, "") -> 0 | K25: =IF(TODAY() >= K$1, L25, "") -> 0 | L25: =IF(TODAY() >= L$1, M25, "") -> 0 | M25: =IF(TODAY() >= M$1, N25, "") -> 0 | ... GF25: =IF(TODAY() >= GF$1, GG25, "") -> 0 | GG25: =IF(TODAY() >= GG$1, HL25, "") -> 0 | GH25: =IF(TODAY() >= GH$1, GI25, "") -> 0 | GI25: =IF(TODAY() >= GI$1, GJ25, "") -> 0 | GJ25: =IF(TODAY() >= GJ$1, GK25, "") -> 0 | GK25: =IF(TODAY() >= GK$1, GL25, "") -> 0 | GL25: =IF(TODAY() >= GL$1, GM25, "") -> 0 | GM25: =IF(TODAY() >= GM$1, GN25, "") -> 0 | GN25: =IF(TODAY() >= GN$1, GO25, "") -> 0 | GO25: =IF(TODAY() >= GO$1, GP25, "") -> 0 | ... MD25: =IF(TODAY() >= MD$1, ME25, "") -> 0 | ME25: =MF25 -> 0 | MF25: =MG25 -> 0 | MG25: =MH25 -> 0 | MH25: =MI25 -> 0 | MI25: =MJ25 -> 0 | MJ25: =MK25 -> 0 | MK25: =ML25 -> 0 | ML25: =MM25 -> 0 | ... MU25: =MV25 -> 0 | MV25: 0 | MW25: 0
A26: Getting the Love You Want | B26: Nook | C26: 298 | D26: =C26 - MAX($F26:MW26) -> 163 | F26: =IF(TODAY() >= F$1, G26, "") -> 135 | G26: =IF(TODAY() >= G$1, H26, "") -> 135 | H26: =IF(TODAY() >= H$1, I26, "") -> 135 | I26: =IF(TODAY() >= I$1, J26, "") -> 135 | J26: =IF(TODAY() >= J$1, K26, "") -> 135 | K26: =IF(TODAY() >= K$1, L26, "") -> 135 | L26: =IF(TODAY() >= L$1, M26, "") -> 135 | M26: =IF(TODAY() >= M$1, N26, "") -> 135 | ... GF26: =IF(TODAY() >= GF$1, GG26, "") -> 135 | GG26: =IF(TODAY() >= GG$1, HL26, "") -> 135 | GH26: =IF(TODAY() >= GH$1, GI26, "") -> 135 | GI26: =IF(TODAY() >= GI$1, GJ26, "") -> 135 | GJ26: =IF(TODAY() >= GJ$1, GK26, "") -> 135 | GK26: =IF(TODAY() >= GK$1, GL26, "") -> 135 | GL26: =IF(TODAY() >= GL$1, GM26, "") -> 135 | GM26: =IF(TODAY() >= GM$1, GN26, "") -> 135 | GN26: =IF(TODAY() >= GN$1, GO26, "") -> 135 | GO26: =IF(TODAY() >= GO$1, GP26, "") -> 135 | ... MD26: =IF(TODAY() >= MD$1, ME26, "") -> 135 | ME26: =MF26 -> 135 | MF26: =MG26 -> 135 | MG26: =MH26 -> 135 | MH26: =MI26 -> 135 | MI26: =MJ26 -> 135 | MJ26: =MK26 -> 135 | MK26: =ML26 -> 135 | ML26: =MM26 -> 135 | ... MU26: =MV26 -> 135 | MV26: 135 | MW26: 135
A27: How to Do the Work | B27: Nook | C27: 274 | D27: =C27 - MAX($F27:MW27) -> 135 | F27: =IF(TODAY() >= F$1, G27, "") -> 139 | G27: =IF(TODAY() >= G$1, H27, "") -> 139 | H27: =IF(TODAY() >= H$1, I27, "") -> 139 | I27: =IF(TODAY() >= I$1, J27, "") -> 139 | J27: =IF(TODAY() >= J$1, K27, "") -> 139 | K27: =IF(TODAY() >= K$1, L27, "") -> 139 | L27: =IF(TODAY() >= L$1, M27, "") -> 139 | M27: =IF(TODAY() >= M$1, N27, "") -> 139 | ... GF27: =IF(TODAY() >= GF$1, GG27, "") -> 139 | GG27: =IF(TODAY() >= GG$1, HL27, "") -> 139 | GH27: =IF(TODAY() >= GH$1, GI27, "") -> 139 | GI27: =IF(TODAY() >= GI$1, GJ27, "") -> 139 | GJ27: =IF(TODAY() >= GJ$1, GK27, "") -> 139 | GK27: =IF(TODAY() >= GK$1, GL27, "") -> 139 | GL27: =IF(TODAY() >= GL$1, GM27, "") -> 139 | GM27: =IF(TODAY() >= GM$1, GN27, "") -> 139 | GN27: =IF(TODAY() >= GN$1, GO27, "") -> 139 | GO27: =IF(TODAY() >= GO$1, GP27, "") -> 139 | ... MD27: =IF(TODAY() >= MD$1, ME27, "") -> 139 | ME27: =MF27 -> 139 | MF27: =MG27 -> 139 | MG27: =MH27 -> 139 | MH27: =MI27 -> 139 | MI27: =MJ27 -> 139 | MJ27: =MK27 -> 139 | MK27: =ML27 -> 139 | ML27: =MM27 -> 139 | ... MU27: =MV27 -> 139 | MV27: 139 | MW27: 139
A28: The Seven Principles for Making Marriage Work | B28: Nook | C28: 272 | D28: =C28 - MAX($F28:MW28) -> 123 | F28: =IF(TODAY() >= F$1, G28, "") -> 149 | G28: =IF(TODAY() >= G$1, H28, "") -> 149 | H28: =IF(TODAY() >= H$1, I28, "") -> 149 | I28: =IF(TODAY() >= I$1, J28, "") -> 149 | J28: =IF(TODAY() >= J$1, K28, "") -> 149 | K28: =IF(TODAY() >= K$1, L28, "") -> 149 | L28: =IF(TODAY() >= L$1, M28, "") -> 149 | M28: =IF(TODAY() >= M$1, N28, "") -> 149 | ... GF28: =IF(TODAY() >= GF$1, GG28, "") -> 149 | GG28: =IF(TODAY() >= GG$1, HL28, "") -> 149 | GH28: =IF(TODAY() >= GH$1, GI28, "") -> 149 | GI28: =IF(TODAY() >= GI$1, GJ28, "") -> 149 | GJ28: =IF(TODAY() >= GJ$1, GK28, "") -> 149 | GK28: =IF(TODAY() >= GK$1, GL28, "") -> 149 | GL28: =IF(TODAY() >= GL$1, GM28, "") -> 149 | GM28: =IF(TODAY() >= GM$1, GN28, "") -> 149 | GN28: =IF(TODAY() >= GN$1, GO28, "") -> 149 | GO28: =IF(TODAY() >= GO$1, GP28, "") -> 149 | ... MD28: =IF(TODAY() >= MD$1, ME28, "") -> 149 | ME28: =MF28 -> 149 | MF28: =MG28 -> 149 | MG28: =MH28 -> 149 | MH28: =MI28 -> 149 | MI28: =MJ28 -> 149 | MJ28: =MK28 -> 149 | MK28: =ML28 -> 149 | ML28: =MM28 -> 149 | ... MU28: =MV28 -> 149 | MV28: 149 | MW28: 149
A29: The DBT Workbook for Narcissistic Abuse and Gaslighting | B29: Nook | C29: 95 | D29: =C29 - MAX($F29:MW29) -> 95 | F29: =IF(TODAY() >= F$1, G29, "") -> 0 | G29: =IF(TODAY() >= G$1, H29, "") -> 0 | H29: =IF(TODAY() >= H$1, I29, "") -> 0 | I29: =IF(TODAY() >= I$1, J29, "") -> 0 | J29: =IF(TODAY() >= J$1, K29, "") -> 0 | K29: =IF(TODAY() >= K$1, L29, "") -> 0 | L29: =IF(TODAY() >= L$1, M29, "") -> 0 | M29: =IF(TODAY() >= M$1, N29, "") -> 0 | ... GF29: =IF(TODAY() >= GF$1, GG29, "") -> 0 | GG29: =IF(TODAY() >= GG$1, HL29, "") -> 0 | GH29: =IF(TODAY() >= GH$1, GI29, "") -> 0 | GI29: =IF(TODAY() >= GI$1, GJ29, "") -> 0 | GJ29: =IF(TODAY() >= GJ$1, GK29, "") -> 0 | GK29: =IF(TODAY() >= GK$1, GL29, "") -> 0 | GL29: =IF(TODAY() >= GL$1, GM29, "") -> 0 | GM29: =IF(TODAY() >= GM$1, GN29, "") -> 0 | GN29: =IF(TODAY() >= GN$1, GO29, "") -> 0 | GO29: =IF(TODAY() >= GO$1, GP29, "") -> 0 | ... MD29: =IF(TODAY() >= MD$1, ME29, "") -> 0 | ME29: =MF29 -> 0 | MF29: =MG29 -> 0 | MG29: =MH29 -> 0 | MH29: =MI29 -> 0 | MI29: =MJ29 -> 0 | MJ29: 0 | MK29: =ML29 -> 0 | ML29: =MM29 -> 0 | MM29: =MN29 -> 0 | MN29: =MO29 -> 0 | MO29: =MP29 -> 0 | MP29: =MQ29 -> 0 | MQ29: =MR29 -> 0 | MR29: =MS29 -> 0 | ... MU29: =MV29 -> 0 | MV29: 0 | MW29: 0
A30: How to Be the Love You Seek | B30: Nook | C30: 261 | D30: =C30 - MAX($F30:MW30) -> 86 | F30: =IF(TODAY() >= F$1, G30, "") -> 175 | G30: =IF(TODAY() >= G$1, H30, "") -> 175 | H30: =IF(TODAY() >= H$1, I30, "") -> 175 | I30: =IF(TODAY() >= I$1, J30, "") -> 175 | J30: =IF(TODAY() >= J$1, K30, "") -> 175 | K30: =IF(TODAY() >= K$1, L30, "") -> 175 | L30: =IF(TODAY() >= L$1, M30, "") -> 175 | M30: =IF(TODAY() >= M$1, N30, "") -> 175 | ... GF30: =IF(TODAY() >= GF$1, GG30, "") -> 175 | GG30: =IF(TODAY() >= GG$1, HL30, "") -> 175 | GH30: =IF(TODAY() >= GH$1, GI30, "") -> 175 | GI30: =IF(TODAY() >= GI$1, GJ30, "") -> 175 | GJ30: =IF(TODAY() >= GJ$1, GK30, "") -> 175 | GK30: =IF(TODAY() >= GK$1, GL30, "") -> 175 | GL30: =IF(TODAY() >= GL$1, GM30, "") -> 175 | GM30: =IF(TODAY() >= GM$1, GN30, "") -> 175 | GN30: =IF(TODAY() >= GN$1, GO30, "") -> 175 | GO30: =IF(TODAY() >= GO$1, GP30, "") -> 175 | ... MD30: =IF(TODAY() >= MD$1, ME30, "") -> 175 | ME30: =MF30 -> 175 | MF30: =MG30 -> 175 | MG30: =MH30 -> 175 | MH30: =MI30 -> 175 | MI30: =MJ30 -> 175 | MJ30: =MK30 -> 175 | MK30: =ML30 -> 175 | ML30: =MM30 -> 175 | ... MU30: =MV30 -> 175 | MV30: 175 | MW30: 175
A31: 天龍八部10: 生死無常 | B31: Libby | C31: 272 | D31: =C31 - MAX($F31:MW31) -> 0 | F31: =IF(TODAY() >= F$1, G31, "") -> 272 | G31: =IF(TODAY() >= G$1, H31, "") -> 272 | H31: =IF(TODAY() >= H$1, I31, "") -> 272 | I31: =IF(TODAY() >= I$1, J31, "") -> 272 | J31: =IF(TODAY() >= J$1, K31, "") -> 272 | K31: =IF(TODAY() >= K$1, L31, "") -> 272 | L31: =IF(TODAY() >= L$1, M31, "") -> 272 | M31: =IF(TODAY() >= M$1, N31, "") -> 272 | ... EI31: =IF(TODAY() >= EI$1, EJ31, "") -> 272 | EJ31: 272 | EK31: 0
A32: 天龍八部9: 會鬥少林 | B32: Libby | C32: 254 | D32: =C32 - MAX($F32:MW32) -> 0 | F32: =IF(TODAY() >= F$1, G32, "") -> 254 | G32: =IF(TODAY() >= G$1, H32, "") -> 254 | H32: =IF(TODAY() >= H$1, I32, "") -> 254 | I32: =IF(TODAY() >= I$1, J32, "") -> 254 | J32: =IF(TODAY() >= J$1, K32, "") -> 254 | K32: =IF(TODAY() >= K$1, L32, "") -> 254 | L32: =IF(TODAY() >= L$1, M32, "") -> 254 | M32: =IF(TODAY() >= M$1, N32, "") -> 254 | ... EJ32: =IF(TODAY() >= EJ$1, EK32, "") -> 254 | EK32: 254 | EL32: 0
A33: 天龍八部8: 小無相功 | B33: Libby | C33: 224 | D33: =C33 - MAX($F33:MW33) -> 0 | F33: =IF(TODAY() >= F$1, G33, "") -> 224 | G33: =IF(TODAY() >= G$1, H33, "") -> 224 | H33: =IF(TODAY() >= H$1, I33, "") -> 224 | I33: =IF(TODAY() >= I$1, J33, "") -> 224 | J33: =IF(TODAY() >= J$1, K33, "") -> 224 | K33: =IF(TODAY() >= K$1, L33, "") -> 224 | L33: =IF(TODAY() >= L$1, M33, "") -> 224 | M33: =IF(TODAY() >= M$1, N33, "") -> 224 | ... EK33: =IF(TODAY() >= EK$1, EL33, "") -> 224 | EL33: 224 | EM33: 0
A34: 天龍八部7: 天山童姥 | B34: Libby | C34: 216 | D34: =C34 - MAX($F34:MW34) -> 0 | F34: =IF(TODAY() >= F$1, G34, "") -> 216 | G34: =IF(TODAY() >= G$1, H34, "") -> 216 | H34: =IF(TODAY() >= H$1, I34, "") -> 216 | I34: =IF(TODAY() >= I$1, J34, "") -> 216 | J34: =IF(TODAY() >= J$1, K34, "") -> 216 | K34: =IF(TODAY() >= K$1, L34, "") -> 216 | L34: =IF(TODAY() >= L$1, M34, "") -> 216 | M34: =IF(TODAY() >= M$1, N34, "") -> 216 | ... EM34: =IF(TODAY() >= EM$1, EN34, "") -> 216 | EN34: 216
A35: 天龍八部6: 金戈鏖兵 | B35: Libby | C35: 275 | D35: =C35 - MAX($F35:MW35) -> 0 | F35: =IF(TODAY() >= F$1, G35, "") -> 275 | G35: =IF(TODAY() >= G$1, H35, "") -> 275 | H35: =IF(TODAY() >= H$1, I35, "") -> 275 | I35: =IF(TODAY() >= I$1, J35, "") -> 275 | J35: =IF(TODAY() >= J$1, K35, "") -> 275 | K35: =IF(TODAY() >= K$1, L35, "") -> 275 | L35: =IF(TODAY() >= L$1, M35, "") -> 275 | M35: =IF(TODAY() >= M$1, N35, "") -> 275 | ... EN35: =IF(TODAY() >= EN$1, EO35, "") -> 275 | EO35: 275 | EP35: 0
A36: 天龍八部5: 千里茫茫 | B36: Libby | C36: 275 | D36: =C36 - MAX($F36:MW36) -> 0 | F36: =IF(TODAY() >= F$1, G36, "") -> 275 | G36: =IF(TODAY() >= G$1, H36, "") -> 275 | H36: =IF(TODAY() >= H$1, I36, "") -> 275 | I36: =IF(TODAY() >= I$1, J36, "") -> 275 | J36: =IF(TODAY() >= J$1, K36, "") -> 275 | K36: =IF(TODAY() >= K$1, L36, "") -> 275 | L36: =IF(TODAY() >= L$1, M36, "") -> 275 | M36: =IF(TODAY() >= M$1, N36, "") -> 275 | ... EO36: =IF(TODAY() >= EO$1, EP36, "") -> 275 | EP36: 275 | EQ36: =IF(TODAY() >= EQ$1, ER36, "") -> 56 | ER36: 56
A37: 天龍八部4: 胡漢恩仇 | B37: Libby | C37: 240 | D37: =C37 - MAX($F37:MW37) -> 0 | F37: =IF(TODAY() >= F$1, G37, "") -> 240 | G37: =IF(TODAY() >= G$1, H37, "") -> 240 | H37: =IF(TODAY() >= H$1, I37, "") -> 240 | I37: =IF(TODAY() >= I$1, J37, "") -> 240 | J37: =IF(TODAY() >= J$1, K37, "") -> 240 | K37: =IF(TODAY() >= K$1, L37, "") -> 240 | L37: =IF(TODAY() >= L$1, M37, "") -> 240 | M37: =IF(TODAY() >= M$1, N37, "") -> 240 | ... EQ37: =IF(TODAY() >= EQ$1, ER37, "") -> 240 | ER37: 240 | ES37: =IF(TODAY() >= ES$1, ET37, "") -> 0 | ET37: =IF(TODAY() >= ET$1, EU37, "") -> 0 | EU37: 0
A38: 天龍八部3: 朱碧雙姝 | B38: Libby | C38: 235 | D38: =C38 - MAX($F38:MW38) -> 0 | F38: =IF(TODAY() >= F$1, G38, "") -> 235 | G38: =IF(TODAY() >= G$1, H38, "") -> 235 | H38: =IF(TODAY() >= H$1, I38, "") -> 235 | I38: =IF(TODAY() >= I$1, J38, "") -> 235 | J38: =IF(TODAY() >= J$1, K38, "") -> 235 | K38: =IF(TODAY() >= K$1, L38, "") -> 235 | L38: =IF(TODAY() >= L$1, M38, "") -> 235 | M38: =IF(TODAY() >= M$1, N38, "") -> 235 | ... ET38: =IF(TODAY() >= ET$1, EU38, "") -> 235 | EU38: 235 | EV38: =IF(TODAY() >= EV$1, EW38, "") -> 16 | EW38: =IF(TODAY() >= EW$1, EX38, "") -> 16 | EX38: =IF(TODAY() >= EX$1, EY38, "") -> 16 | EY38: 16
A39: 天龍八部2: 六脈神劍 | B39: Libby | C39: 235 | D39: =C39 - MAX($F39:MW39) -> 0 | F39: =IF(TODAY() >= F$1, G39, "") -> 235 | G39: =IF(TODAY() >= G$1, H39, "") -> 235 | H39: =IF(TODAY() >= H$1, I39, "") -> 235 | I39: =IF(TODAY() >= I$1, J39, "") -> 235 | J39: =IF(TODAY() >= J$1, K39, "") -> 235 | K39: =IF(TODAY() >= K$1, L39, "") -> 235 | L39: =IF(TODAY() >= L$1, M39, "") -> 235 | M39: =IF(TODAY() >= M$1, N39, "") -> 235 | ... EX39: =IF(TODAY() >= EX$1, EY39, "") -> 235 | EY39: 235 | EZ39: 188 | FA39: =IF(TODAY() >= FA$1, FB39, "") -> 86 | FB39: 86 | FC39: 0
A40: 天龍八部1: 無量玉壁 | B40: Libby | C40: 252 | D40: =C40 - MAX($F40:MW40) -> 0 | F40: =IF(TODAY() >= F$1, G40, "") -> 252 | G40: =IF(TODAY() >= G$1, H40, "") -> 252 | H40: =IF(TODAY() >= H$1, I40, "") -> 252 | I40: =IF(TODAY() >= I$1, J40, "") -> 252 | J40: =IF(TODAY() >= J$1, K40, "") -> 252 | K40: =IF(TODAY() >= K$1, L40, "") -> 252 | L40: =IF(TODAY() >= L$1, M40, "") -> 252 | M40: =IF(TODAY() >= M$1, N40, "") -> 252 | ... FB40: =IF(TODAY() >= FB$1, FC40, "") -> 252 | FC40: 252 | FD40: 109 | FE40: =IF(TODAY() >= FE$1, FF40, "") -> 0 | FF40: =IF(TODAY() >= FF$1, FG40, "") -> 0 | FG40: =IF(TODAY() >= FG$1, FH40, "") -> 0 | FH40: =IF(TODAY() >= FH$1, FI40, "") -> 0 | FI40: =IF(TODAY() >= FI$1, FJ40, "") -> 0 | FJ40: =IF(TODAY() >= FJ$1, FK40, "") -> 0 | FK40: =IF(TODAY() >= FK$1, FL40, "") -> 0 | FL40: =IF(TODAY() >= FL$1, FM40, "") -> 0 | ... GF40: =IF(TODAY() >= GF$1, GG40, "") -> 0 | GG40: 0 | GH40: =IF(TODAY() >= GH$1, GI40, "") | GI40: =IF(TODAY() >= GI$1, GJ40, "") | GJ40: =IF(TODAY() >= GJ$1, GK40, "") | GK40: =IF(TODAY() >= GK$1, GL40, "") | GL40: =IF(TODAY() >= GL$1, GM40, "") | GM40: =IF(TODAY() >= GM$1, GN40, "") | GN40: =IF(TODAY() >= GN$1, GO40, "") | GO40: =IF(TODAY() >= GO$1, GP40, "") | ... HK40: =IF(TODAY() >= HK$1, HL40, "")
A41: 三體2:黑暗森林 | B41: Libby | C41: 664 | D41: =C41 - MAX($F41:MW41) -> 0 | F41: =IF(TODAY() >= F$1, G41, "") -> 664 | G41: =IF(TODAY() >= G$1, H41, "") -> 664 | H41: =IF(TODAY() >= H$1, I41, "") -> 664 | I41: =IF(TODAY() >= I$1, J41, "") -> 664 | J41: =IF(TODAY() >= J$1, K41, "") -> 664 | K41: =IF(TODAY() >= K$1, L41, "") -> 664 | L41: =IF(TODAY() >= L$1, M41, "") -> 664 | M41: =IF(TODAY() >= M$1, N41, "") -> 664 | ... GF41: =IF(TODAY() >= GF$1, GG41, "") -> 664 | GG41: =IF(TODAY() >= GG$1, HL41, "") -> 664 | GH41: =IF(TODAY() >= GH$1, GI41, "") -> 664 | GI41: =IF(TODAY() >= GI$1, GJ41, "") -> 664 | GJ41: =IF(TODAY() >= GJ$1, GK41, "") -> 664 | GK41: =IF(TODAY() >= GK$1, GL41, "") -> 664 | GL41: =IF(TODAY() >= GL$1, GM41, "") -> 664 | GM41: =IF(TODAY() >= GM$1, GN41, "") -> 664 | GN41: =IF(TODAY() >= GN$1, GO41, "") -> 664 | GO41: =IF(TODAY() >= GO$1, GP41, "") -> 664 | ... HV41: =IF(TODAY() >= HV$1, HW41, "") -> 664 | HW41: 664 | HX41: =IF(TODAY() >= HX$1, HY41, "") -> 463 | HY41: =IF(TODAY() >= HY$1, HZ41, "") -> 463 | HZ41: =IF(TODAY() >= HZ$1, IA41, "") -> 463 | IA41: =IF(TODAY() >= IA$1, IB41, "") -> 463 | IB41: =IF(TODAY() >= IB$1, IC41, "") -> 463 | IC41: =IF(TODAY() >= IC$1, ID41, "") -> 463 | ID41: =IF(TODAY() >= ID$1, IE41, "") -> 463 | IE41: =IF(TODAY() >= IE$1, IF41, "") -> 463 | ... IP41: =IF(TODAY() >= IP$1, IQ41, "") -> 463 | IQ41: 463 | IR41: =IF(TODAY() >= IR$1, IS41, "") -> 337 | IS41: =IF(TODAY() >= IS$1, IT41, "") -> 337 | IT41: =IF(TODAY() >= IT$1, IU41, "") -> 337 | IU41: =IF(TODAY() >= IU$1, IV41, "") -> 337 | IV41: 337 | IW41: =IF(TODAY() >= IW$1, IX41, "") -> 214 | IX41: =IF(TODAY() >= IX$1, IY41, "") -> 214 | IY41: =IF(TODAY() >= IY$1, IZ41, "") -> 214 | IZ41: 214 | JA41: =IF(TODAY() >= JA$1, JB41, "") -> 168 | JB41: 168 | JC41: =IF(TODAY() >= JC$1, JD41, "") -> 124 | JD41: =IF(TODAY() >= JD$1, JE41, "") -> 124 | JE41: =IF(TODAY() >= JE$1, JF41, "") -> 124 | JF41: =IF(TODAY() >= JF$1, JG41, "") -> 124 | JG41: 124 | JH41: =IF(TODAY() >= JH$1, JI41, "") -> 22 | JI41: =IF(TODAY() >= JI$1, JJ41, "") -> 22 | JJ41: =IF(TODAY() >= JJ$1, JK41, "") -> 22 | JK41: =IF(TODAY() >= JK$1, JL41, "") -> 22 | JL41: =IF(TODAY() >= JL$1, JM41, "") -> 22 | JM41: =IF(TODAY() >= JM$1, JN41, "") -> 22 | JN41: =IF(TODAY() >= JN$1, JO41, "") -> 22 | JO41: =IF(TODAY() >= JO$1, JP41, "") -> 22 | ... JW41: =IF(TODAY() >= JW$1, JX41, "") -> 22 | JX41: 22 | JY41: =IF(TODAY() >= JY$1, JZ41, "") -> 0 | JZ41: =IF(TODAY() >= JZ$1, KA41, "") -> 0 | KA41: =IF(TODAY() >= KA$1, KB41, "") -> 0 | KB41: =IF(TODAY() >= KB$1, KC41, "") -> 0 | KC41: =IF(TODAY() >= KC$1, KD41, "") -> 0 | KD41: =IF(TODAY() >= KD$1, KE41, "") -> 0 | KE41: =IF(TODAY() >= KE$1, KF41, "") -> 0 | KF41: =IF(TODAY() >= KF$1, KG41, "") -> 0 | ... KP41: =IF(TODAY() >= KP$1, KQ41, "") -> 0 | KQ41: 0 | KR41: =IF(TODAY() >= KR$1, KS41, "") | KS41: =IF(TODAY() >= KS$1, KT41, "") | KT41: =IF(TODAY() >= KT$1, KU41, "") | KU41: =IF(TODAY() >= KU$1, KV41, "") | KV41: =IF(TODAY() >= KV$1, KW41, "") | KW41: =IF(TODAY() >= KW$1, KX41, "") | KX41: =IF(TODAY() >= KX$1, KY41, "") | KY41: =IF(TODAY() >= KY$1, KZ41, "")
A42: 三體1:地球往事 | B42: Libby | C42: 405 | D42: =C42 - MAX($F42:MW42) -> 0 | F42: =IF(TODAY() >= F$1, G42, "") -> 405 | G42: =IF(TODAY() >= G$1, H42, "") -> 405 | H42: =IF(TODAY() >= H$1, I42, "") -> 405 | I42: =IF(TODAY() >= I$1, J42, "") -> 405 | J42: =IF(TODAY() >= J$1, K42, "") -> 405 | K42: =IF(TODAY() >= K$1, L42, "") -> 405 | L42: =IF(TODAY() >= L$1, M42, "") -> 405 | M42: =IF(TODAY() >= M$1, N42, "") -> 405 | ... GF42: =IF(TODAY() >= GF$1, GG42, "") -> 405 | GG42: =IF(TODAY() >= GG$1, HL42, "") -> 405 | GH42: =IF(TODAY() >= GH$1, GI42, "") -> 405 | GI42: =IF(TODAY() >= GI$1, GJ42, "") -> 405 | GJ42: =IF(TODAY() >= GJ$1, GK42, "") -> 405 | GK42: =IF(TODAY() >= GK$1, GL42, "") -> 405 | GL42: =IF(TODAY() >= GL$1, GM42, "") -> 405 | GM42: =IF(TODAY() >= GM$1, GN42, "") -> 405 | GN42: =IF(TODAY() >= GN$1, GO42, "") -> 405 | GO42: =IF(TODAY() >= GO$1, GP42, "") -> 405 | ... JY42: =IF(TODAY() >= JY$1, JZ42, "") -> 405 | JZ42: 405 | KA42: 291 | KB42: =IF(TODAY() >= KB$1, KC42, "") -> 247 | KC42: =IF(TODAY() >= KC$1, KD42, "") -> 247 | KD42: =IF(TODAY() >= KD$1, KE42, "") -> 247 | KE42: 247 | KF42: 172 | KG42: =IF(TODAY() >= KG$1, KH42, "") -> 111 | KH42: =IF(TODAY() >= KH$1, KI42, "") -> 111 | KI42: =IF(TODAY() >= KI$1, KJ42, "") -> 111 | KJ42: =IF(TODAY() >= KJ$1, KK42, "") -> 111 | KK42: =IF(TODAY() >= KK$1, KL42, "") -> 111 | KL42: 111 | KM42: =IF(TODAY() >= KM$1, KN42, "") -> 34 | KN42: =IF(TODAY() >= KN$1, KO42, "") -> 34 | KO42: 34 | KP42: =IF(TODAY() >= KP$1, KQ42, "") -> 0 | KQ42: =IF(TODAY() >= KQ$1, KR42, "") -> 0 | KR42: =IF(TODAY() >= KR$1, KS42, "") -> 0 | KS42: =IF(TODAY() >= KS$1, KT42, "") -> 0 | KT42: =IF(TODAY() >= KT$1, KU42, "") -> 0 | KU42: =IF(TODAY() >= KU$1, KV42, "") -> 0 | KV42: =IF(TODAY() >= KV$1, KW42, "") -> 0 | KW42: =IF(TODAY() >= KW$1, KX42, "") -> 0 | ... MD42: =IF(TODAY() >= MD$1, ME42, "") -> 0 | ME42: =MF42 -> 0 | MF42: =MG42 -> 0 | MG42: =MH42 -> 0 | MH42: =MI42 -> 0 | MI42: =MJ42 -> 0 | MJ42: =MK42 -> 0 | MK42: =ML42 -> 0 | ML42: =MM42 -> 0 | ... MU42: =MV42 -> 0 | MV42: 0 | MW42: 0
A43: Tomorrow, Tomorrow, and Tomorrow | B43: Libby | C43: 628 | D43: =C43 - MAX($F43:MW43) -> 0 | F43: =IF(TODAY() >= F$1, G43, "") -> 628 | G43: =IF(TODAY() >= G$1, H43, "") -> 628 | H43: =IF(TODAY() >= H$1, I43, "") -> 628 | I43: =IF(TODAY() >= I$1, J43, "") -> 628 | J43: =IF(TODAY() >= J$1, K43, "") -> 628 | K43: =IF(TODAY() >= K$1, L43, "") -> 628 | L43: =IF(TODAY() >= L$1, M43, "") -> 628 | M43: =IF(TODAY() >= M$1, N43, "") -> 628 | ... GF43: =IF(TODAY() >= GF$1, GG43, "") -> 628 | GG43: =IF(TODAY() >= GG$1, HL43, "") -> 628 | GH43: =IF(TODAY() >= GH$1, GI43, "") -> 628 | GI43: =IF(TODAY() >= GI$1, GJ43, "") -> 628 | GJ43: =IF(TODAY() >= GJ$1, GK43, "") -> 628 | GK43: =IF(TODAY() >= GK$1, GL43, "") -> 628 | GL43: =IF(TODAY() >= GL$1, GM43, "") -> 628 | GM43: =IF(TODAY() >= GM$1, GN43, "") -> 628 | GN43: =IF(TODAY() >= GN$1, GO43, "") -> 628 | GO43: =IF(TODAY() >= GO$1, GP43, "") -> 628 | ... LN43: =IF(TODAY() >= LN$1, LO43, "") -> 628 | LO43: 628 | LP43: =IF(TODAY() >= LP$1, LQ43, "") -> 531 | LQ43: 531 | LR43: =IF(TODAY() >= LR$1, LS43, "") -> 476 | LS43: =IF(TODAY() >= LS$1, LT43, "") -> 476 | LT43: 476 | LU43: 369 | LV43: 283 | LW43: 199 | LX43: 181 | LY43: 140 | LZ43: 83 | MA43: =IF(TODAY() >= MA$1, MB43, "") -> 61 | MB43: =IF(TODAY() >= MB$1, MC43, "") -> 61 | MC43: 61 | MD43: =IF(TODAY() >= MD$1, ME43, "") -> 0 | ME43: =MF43 -> 0 | MF43: =MG43 -> 0 | MG43: =MH43 -> 0 | MH43: =MI43 -> 0 | MI43: =MJ43 -> 0 | MJ43: =MK43 -> 0 | MK43: =ML43 -> 0 | ML43: =MM43 -> 0 | ... MU43: =MV43 -> 0 | MV43: 0 | MW43: 0
A44: Think Again | B44: physical | C44: 259 | D44: =C44 - MAX($F44:MW44) -> 0 | F44: =IF(TODAY() >= F$1, G44, "") -> 259 | G44: =IF(TODAY() >= G$1, H44, "") -> 259 | H44: =IF(TODAY() >= H$1, I44, "") -> 259 | I44: =IF(TODAY() >= I$1, J44, "") -> 259 | J44: =IF(TODAY() >= J$1, K44, "") -> 259 | K44: =IF(TODAY() >= K$1, L44, "") -> 259 | L44: =IF(TODAY() >= L$1, M44, "") -> 259 | M44: =IF(TODAY() >= M$1, N44, "") -> 259 | ... GF44: =IF(TODAY() >= GF$1, GG44, "") -> 259 | GG44: =IF(TODAY() >= GG$1, HL44, "") -> 259 | GH44: =IF(TODAY() >= GH$1, GI44, "") -> 259 | GI44: =IF(TODAY() >= GI$1, GJ44, "") -> 259 | GJ44: =IF(TODAY() >= GJ$1, GK44, "") -> 259 | GK44: =IF(TODAY() >= GK$1, GL44, "") -> 259 | GL44: =IF(TODAY() >= GL$1, GM44, "") -> 259 | GM44: =IF(TODAY() >= GM$1, GN44, "") -> 259 | GN44: =IF(TODAY() >= GN$1, GO44, "") -> 259 | GO44: =IF(TODAY() >= GO$1, GP44, "") -> 259 | ... LB44: =IF(TODAY() >= LB$1, LC44, "") -> 259 | LC44: 259 | LD44: =IF(TODAY() >= LD$1, LE44, "") -> 203 | LE44: =IF(TODAY() >= LE$1, LF44, "") -> 203 | LF44: =IF(TODAY() >= LF$1, LG44, "") -> 203 | LG44: =IF(TODAY() >= LG$1, LH44, "") -> 203 | LH44: =IF(TODAY() >= LH$1, LI44, "") -> 203 | LI44: =IF(TODAY() >= LI$1, LJ44, "") -> 203 | LJ44: =IF(TODAY() >= LJ$1, LK44, "") -> 203 | LK44: =IF(TODAY() >= LK$1, LL44, "") -> 203 | ... LY44: =IF(TODAY() >= LY$1, LZ44, "") -> 203 | LZ44: 203 | MA44: =IF(TODAY() >= MA$1, MB44, "") -> 185 | MB44: =IF(TODAY() >= MB$1, MC44, "") -> 185 | MC44: =IF(TODAY() >= MC$1, MD44, "") -> 185 | MD44: =IF(TODAY() >= MD$1, ME44, "") -> 185 | ME44: =MF44 -> 185 | MF44: =MG44 -> 185 | MG44: =MH44 -> 185 | MH44: =MI44 -> 185 | MI44: =MJ44 -> 185 | MJ44: =MK44 -> 185 | MK44: =ML44 -> 185 | ML44: =MM44 -> 185 | ... MU44: =MV44 -> 185 | MV44: 185 | MW44: 185
A45: Chip War | B45: Kindle | C45: 363 | D45: =C45 - MAX($F45:MW45) -> 0 | F45: =IF(TODAY() >= F$1, G45, "") -> 363 | G45: =IF(TODAY() >= G$1, H45, "") -> 363 | H45: =IF(TODAY() >= H$1, I45, "") -> 363 | I45: =IF(TODAY() >= I$1, J45, "") -> 363 | J45: =IF(TODAY() >= J$1, K45, "") -> 363 | K45: =IF(TODAY() >= K$1, L45, "") -> 363 | L45: =IF(TODAY() >= L$1, M45, "") -> 363 | M45: =IF(TODAY() >= M$1, N45, "") -> 363 | ... GF45: =IF(TODAY() >= GF$1, GG45, "") -> 363 | GG45: =IF(TODAY() >= GG$1, HL45, "") -> 363 | GH45: =IF(TODAY() >= GH$1, GI45, "") -> 363 | GI45: =IF(TODAY() >= GI$1, GJ45, "") -> 363 | GJ45: =IF(TODAY() >= GJ$1, GK45, "") -> 363 | GK45: =IF(TODAY() >= GK$1, GL45, "") -> 363 | GL45: =IF(TODAY() >= GL$1, GM45, "") -> 363 | GM45: =IF(TODAY() >= GM$1, GN45, "") -> 363 | GN45: =IF(TODAY() >= GN$1, GO45, "") -> 363 | GO45: =IF(TODAY() >= GO$1, GP45, "") -> 363 | ... MD45: =IF(TODAY() >= MD$1, ME45, "") -> 363 | ME45: 363 | MF45: 363 | MG45: 306 | MH45: 306 | MI45: 306 | MJ45: 306 | MK45: 240 | ML45: 202 | MM45: 202 | MN45: 202 | MO45: 146 | MP45: 146 | MQ45: 146 | MR45: 146 | MS45: 115 | MT45: 86 | MU45: 55 | MV45: 49 | MW45: 49
A46: Breath: The New Science of a Lost Art | B46: Libby | C46: 304 | D46: =C46 - MAX($F46:MW46) -> 0 | F46: =IF(TODAY() >= F$1, G46, "") -> 304 | G46: =IF(TODAY() >= G$1, H46, "") -> 304 | H46: =IF(TODAY() >= H$1, I46, "") -> 304 | I46: =IF(TODAY() >= I$1, J46, "") -> 304 | J46: =IF(TODAY() >= J$1, K46, "") -> 304 | K46: =IF(TODAY() >= K$1, L46, "") -> 304 | L46: =IF(TODAY() >= L$1, M46, "") -> 304 | M46: =IF(TODAY() >= M$1, N46, "") -> 304 | ... FR46: =IF(TODAY() >= FR$1, FS46, "") -> 304 | FS46: 304 | FT46: 0 | FU46: 0 | FV46: =IF(TODAY() >= FV$1, FW46, "") -> 0 | FW46: =IF(TODAY() >= FW$1, FX46, "") -> 0 | FX46: =IF(TODAY() >= FX$1, FY46, "") -> 0 | FY46: =IF(TODAY() >= FY$1, FZ46, "") -> 0 | FZ46: =IF(TODAY() >= FZ$1, GA46, "") -> 0 | GA46: =IF(TODAY() >= GA$1, GB46, "") -> 0 | GB46: =IF(TODAY() >= GB$1, GC46, "") -> 0 | GC46: =IF(TODAY() >= GC$1, GD46, "") -> 0 | ... GF46: =IF(TODAY() >= GF$1, GG46, "") -> 0 | GG46: 0
A47: The Metamorphosis | B47: Libby | C47: 77 | D47: =C47 - MAX($F47:MW47) -> 0 | F47: =IF(TODAY() >= F$1, G47, "") -> 77 | G47: =IF(TODAY() >= G$1, H47, "") -> 77 | H47: =IF(TODAY() >= H$1, I47, "") -> 77 | I47: =IF(TODAY() >= I$1, J47, "") -> 77 | J47: =IF(TODAY() >= J$1, K47, "") -> 77 | K47: =IF(TODAY() >= K$1, L47, "") -> 77 | L47: =IF(TODAY() >= L$1, M47, "") -> 77 | M47: =IF(TODAY() >= M$1, N47, "") -> 77 | ... CS47: =IF(TODAY() >= CS$1, CT47, "") -> 77 | CT47: 77 | CU47: =IF(TODAY() >= CU$1, CV47, "") -> 0 | CV47: =IF(TODAY() >= CV$1, CW47, "") -> 0 | CW47: =IF(TODAY() >= CW$1, CX47, "") -> 0 | CX47: =IF(TODAY() >= CX$1, CY47, "") -> 0 | CY47: =IF(TODAY() >= CY$1, CZ47, "") -> 0 | CZ47: =IF(TODAY() >= CZ$1, DA47, "") -> 0 | DA47: =IF(TODAY() >= DA$1, DB47, "") -> 0 | DB47: =IF(TODAY() >= DB$1, DC47, "") -> 0 | ... FR47: =IF(TODAY() >= FR$1, FS47, "") -> 0 | FS47: 0 | FT47: 0 | FU47: 0 | FV47: =IF(TODAY() >= FV$1, FW47, "") -> 0 | FW47: =IF(TODAY() >= FW$1, FX47, "") -> 0 | FX47: =IF(TODAY() >= FX$1, FY47, "") -> 0 | FY47: =IF(TODAY() >= FY$1, FZ47, "") -> 0 | FZ47: =IF(TODAY() >= FZ$1, GA47, "") -> 0 | GA47: =IF(TODAY() >= GA$1, GB47, "") -> 0 | GB47: =IF(TODAY() >= GB$1, GC47, "") -> 0 | GC47: =IF(TODAY() >= GC$1, GD47, "") -> 0 | ... GF47: =IF(TODAY() >= GF$1, GG47, "") -> 0 | GG47: 0
A48: Your Somatic Therapy Toolbox | B48: Kindle | C48: 153 | D48: =C48 - MAX($F48:MW48) -> 153 | F48: =IF(TODAY() >= F$1, G48, "") -> 0 | G48: =IF(TODAY() >= G$1, H48, "") -> 0 | H48: 0
A49: Notes on Being a Man | B49: Nook | C49: 282 | D49: =C49 - MAX($F49:MW49) -> 159 | F49: =IF(TODAY() >= F$1, G49, "") -> 123 | G49: =IF(TODAY() >= G$1, H49, "") -> 123 | H49: 123 | I49: =IF(TODAY() >= I$1, J49, "") -> 0 | J49: =IF(TODAY() >= J$1, K49, "") -> 0 | K49: =IF(TODAY() >= K$1, L49, "") -> 0 | L49: =IF(TODAY() >= L$1, M49, "") -> 0 | M49: =IF(TODAY() >= M$1, N49, "") -> 0 | N49: =IF(TODAY() >= N$1, O49, "") -> 0 | O49: =IF(TODAY() >= O$1, P49, "") -> 0 | P49: =IF(TODAY() >= P$1, Q49, "") -> 0 | ... FR49: =IF(TODAY() >= FR$1, FS49, "") -> 0 | FS49: 0 | FT49: 0 | FU49: 0 | FV49: =IF(TODAY() >= FV$1, FW49, "") -> 0 | FW49: =IF(TODAY() >= FW$1, FX49, "") -> 0 | FX49: =IF(TODAY() >= FX$1, FY49, "") -> 0 | FY49: =IF(TODAY() >= FY$1, FZ49, "") -> 0 | FZ49: =IF(TODAY() >= FZ$1, GA49, "") -> 0 | GA49: =IF(TODAY() >= GA$1, GB49, "") -> 0 | GB49: =IF(TODAY() >= GB$1, GC49, "") -> 0 | GC49: =IF(TODAY() >= GC$1, GD49, "") -> 0 | ... GF49: =IF(TODAY() >= GF$1, GG49, "") -> 0 | GG49: 0
F50: =IF(TODAY() >= F$1, G50, "") | G50: =IF(TODAY() >= G$1, H50, "") | H50: =IF(TODAY() >= H$1, I50, "") | I50: =IF(TODAY() >= I$1, J50, "") | J50: =IF(TODAY() >= J$1, K50, "") | K50: =IF(TODAY() >= K$1, L50, "") | L50: =IF(TODAY() >= L$1, M50, "") | M50: =IF(TODAY() >= M$1, N50, "") | ... DX50: =IF(TODAY() >= DX$1, DY50, "")
A51: metadata
A52: daily reading goal (pages) | B52: 15

Sheet LC
A1: Week | B1: Goal | C1: Resource Focus | D1: Unit | E1: NeetCode Video | F1: LeetCode | G1: GeeksForGeeks | H1: Date | I1: Progress
A2: 1 | B2: Master basic array manipulations, frequency counting, and hash map usage. | C2: NeetCode's "Arrays & Hasing" section | D2: 1 | E2: Valid Anagram, Contains Duplicate | F2: 217, 242 | G2: Basic Array operations, Hash Map introduction
D3: 2 | E3: Two Sum, Group Anagrams | F3: 1, 49 | G3: Two Pointer technique
D4: 3 | E4: Top K Frequent Elements, Product of Array Except Self | F4: 347, 238 | G4: Frequency counting using hash maps
D5: 4 | E5: Longest Consecutive Sequence | F5: 128 | G5: Set data structure properties
D6: 5 | E6: Revisit one or two problems you struggled with this week. Try a related "Easy" problem on LeetCode not covered by NeetCode in this category.
A7: 2 | B7: Understand two-pointer techniques and the sliding window patterning for array/string problems. | C7: NeetCode's "Two Pointers" and "Sliding Window" sections. | D7: 1 | E7: Valid Palindrome, Three Sum | F7: 125, 15 | G7: Advanced Two Pointer applications
D8: 2 | E8: Container With Most Water | F8: 11 | G8: -
D9: 3 | E9: Best Time to Buy and Sell Stock, Longest Substring Without Repeating Characters | F9: 121, 3 | G9: Sliding Window explained visually
D10: 4 | E10: Longest Repeating Character Replacement, Permutation in String | F10: 424, 567 | G10: -
D11: 5 | E11: Revisit one or two problems you struggled this week. Find a new "Medium" sliding window problem on LeetCode.
A12: 3 | B12: Master stack usage for valid parentheses/monotonous stack patterns and binary search applications. | C12: NeetCode's "Stack" and "Binary Search" sections. | D12: 1 | E12: Valid Parentheses, Min Stack | F12: 20, 155 | G12: Stack data structure with examples
D13: 2 | E13: Evaluate Reverse Polish Notation, Daily Temperatures | F13: 150, 739 | G13: -
D14: 3 | E14: Binary Search, Search a 2D Matrix | F14: 704, 74 | G14: Binary Search algorithm detailed
D15: 4 | E15: Koko Eating Bananas, Find Minimum in Rotated Sorted Array | F15: 875, 153 | G15: -
D16: 5 | E16: Revisit one or two problems you struggled with this week. Try a related "Easy/Medium" stack or binary search problem on LeetCode.
A17: 4 | B17: Understand linked list manipulations and basic tree traversals | C17: NeetCode's "Linked List" and "Trees" sections. | D17: 1 | E17: Reverse Linked List, Merge Two Sorted Lists | F17: 206, 21 | G17: Linked List operations (insertion, deletion)
D18: 2 | E18: Reorder List, Remove Nth Node From End of List | F18: 143, 19 | G18: -
D19: 3 | E19: Invert Binary Tree, Maximum Depth of Binary Tree | F19: 226, 104 | G19: Tree traversals (DFS, BFS)
D20: 4 | E20: Same Tree, Subtree of Another Tree | F20: 100, 572 | G20: -
D21: 5 | E21: Revisit one or two problems you struggled with this week. Try a related "Easy/Medium" linked list or tree problem on LeetCode.
A22: 5 | B22: Deepen tree knowledge (BSTs, BFS traversals) and introduce backtracking | C22: NeetCode's "Trees" and "Backtracking" sections. | D22: 1 | E22: Level Order Traversal, Validate Binary Search Tree | F22: 102, 98 | G22: BFS vs DFS in trees, properties of BST
D23: 2 | E23: Key Smallest Element in a BST, Lowest Common Ancestor of a BST | F23: 230, 235 | G23: -
D24: 3 | E24: Combinations, Permutations | F24: 77, 46 | G24: Understanding recursion, and backtracking concept
D25: 4 | E25: Subsets, Combination Sum | F25: 78, 39 | G25: -
D26: 5 | E26: Revisit one or two problems you struggled with this week. Attempt a new "Medium" backtracking problem on LeetCode.
A27: 6 | B27: Understand Trie data structure and Heap/Priority Queue application | C27: NeetCode's "Tries" and "Heap/Priority Queue" sections | D27: 1 | E27: Implement Trie, Design Add and Search Words Data Structure | F27: 208, 211 | G27: Tried data structure introduction
D28: 2 | E28: Kth Largest Element in an Array, Top K Frequent Elements | F28: 215, 347 | G28: Heap data structure, Min-Heap vs Max-Heap
D29: 3 | E29: K Closest Points to Origin, Find Median from Data Stream | F29: 973, 295 | G29: -
D30: 4 | E30: Number of Islands | F30: 200 | G30: Graph representations (adjacency list/matrix), BFS/DFS on graphs
D31: 5 | E31: Revisit one or two problems you struggled with this week. Try a new "Medium" heap or graph (BFS/DFS) problem.
A32: 7 | B32: Deepen graph knowledge (topological sort, advanced traversals) and understand interval problems. | C32: NeetCode's "Graphs" and "Intervals" sections | D32: 1 | E32: Clone Graph, Course Schedule | F32: 133, 207 | G32: Topological Sort algorithm
D33: 2 | E33: Pacific Atlantic Water Flow, Number of Connected Components | F33: 417, 323 | G33: -
D34: 3 | E34: Merge Intervals, Insert Interval | F34: 56, 57 | G34: Interval merging patterns
D35: 4 | E35: Non-overlapping Intervals | F35: 435 | G35: -
D36: 5 | E36: Revisit one or two problems you struggled with this week. Try a new "Medium/Hard" graph or interval problem.
A37: 8 | B37: Grasp the core principles of Dynamic Programming. This is often the most challenging, so focus on understanding. | C37: NeetCode's "Dynamic Programming" section. | D37: 1 | E37: Climbing Stairs, House Robber | F37: 70, 198 | G37: Introduction to DP, memoization vs tabulation.
D38: 2 | E38: Longest Common Subsequence, Word Break | F38: 1143, 139 | G38: -
D39: 3 | E39: Combination Sum IV, Coin Change | F39: 377, 322 | G39: -
D40: 4 | E40: Longest Increasing Subsequence, House Robber II | F40: 300, 213 | G40: -
D41: 5 | E41: Final Review & Mock Interview (Self-Administered). Pick 2-3 random "Medium" problems from the NeetCode 150 that you haven't recently practiced. Solve them under timed conditions (e.g., 20-30 min per problem). Verbalize your thought process as if in a real interview. Review your solution for optimality and clarity.

Sheet ML
A1: Week | B1: Theme | C1: Goal | D1: Unit | E1: Topic | F1: Reading | G1: Video | H1: Exercise | I1: Project | J1: Date | K1: Progress | L1: Key Resources
A2: 1 | B2: Foundations & Introduction to ML | C2: Understand the basics of data, Python for ML, and the ML workflow | D2: 1 | E2: Introduction to Machine Learning (What is ML? Supervised vs. Unsupervised vs. Reinforcement Learning). Key terminology. | F2: Gèron, Chapter 1: The Machine Learning Landscape (skim for overview), Towards Data Science: "What is Machine Learning?" (search for a beginner-friendly article). | G2: ML Course: Week 1, "Introduction" and "Linear Regression with One Variable" (focus on the "What is ML" part). | H2: Reflect on examples of ML in daily life. Differentiate between supervised and unsupervised learning examples | L2: "Hands-On Machine Learning with Scikit-Learn, Keras, and TensorFlow" by Aurèlien Gèron (2nd or 3rd Edition): This book is a goldminefor practical examples and theoretical understanding. We'll refer to it as "Gèron" for brevity.
D3: 2 | E3: Python Crash Course for ML (Review of essential data types, control flow, functions) | F3: Python official tutorial (sections on basic types, control flow, functions) or a "Python for Data Science" crash course blog | G3: "Python for Everybody" (Coursera) - first few modules, or a quick YouTube "Python Crash Course" for data science. | H3: Write simple Python functions: .g., a function to calculate the average of a list, a function to check if a number is even/odd. | L3: Andrew Ng's Machine Learning Specialization (Coursera): Excellent for foundational understanding. We'll refer to it as "Ng ML Course".
D4: 3 | E4: NumPy Basics (Arrays, operations, broadcasting). | F4: NumPy Official Documentation: "The Absolute Basics for Beginners" | G4: Krish Naik's "Numpy Tutorial for Data Science" (YouTube) or DataCamp's "NumPy Tutorial: The Basics". | H4: Create 1D, 2D, and 3D NumPy arrays. Perform basic array operations (addition, multiplication, dot product). Practice array slicing and indexing. | L4: Scikit-learn documentation: Official documentation is invaluable.
D5: 4 | E5: Pandas Basics (DataFrames, reading CSV, basic data manipulation) | F5: Pandas Official Documentation: "10 minutes to pandas" (or a similar beginner guide) | G5: Corey Schafer's "Pandas Tutorial" (YouTube - Part 1) or DataCamp's "Pandas Tutorial: The Ultimate Guide for Beginners". | H5: Load a small CSV file (e.g., a dummy dataset you create or download). Inspect data: .head(), .info(), .describe(), .shape. Select columns, filter rows based on conditions. | L5: Kaggle: For datasets and practice competitions.
D6: 5 | E6: Matplotlib/Seaborn Basics (Basic plotting, data visualization for exploration). Practice: Basic data loading, inspection, and simple plotting of a dataset (e.g., Iris or Boston Housing) | F6: Matplotlib/Seaborn beginner tutorials (e.g., from Towards Data Science, Real Python) | G6: Krish Naik's "Matplotlib Tutorial" and "Seaborn Tutorial" (YouTube). | H6: Using the Pandas DataFrame from yesterday, create: a histogram of a numerical column; a scatter plot of two numerical columns; a bar chart of a categorical column's counts. | L6: Google Colab/Jupyter Notebooks: For coding
A7: 2 | B7: Data Preprocessing & Exploratory Data Analysis (EDA) | C7: Learn how to prepare data for ML models | D7: 1 | E7: Missing Data Handling (Imputation techniques) | F7: Gèron, Chapter 2: End-to-End Machine Learning Project (focus on missing value handling). Scikit-learn Imputer documentation. | G7: "Handling Missing Values" tutorial (e.g., from DataCamp, Krish Naik). | H7: On the Titanic dataset: identify columns with missing values (.isnull().sum()); practice dropping rows/columns with missing values; practice fillna() with mean/median for numerical, and mode for categorical.
D8: 2 | E8: Feature Scaling (Normalization, Standization) | F8: Gèron, Chapter 2 (section on feature scaling). Scikit-learn StandardScaler and MinMaxScaler documentation. | G8: "Feature Scaling Explained" (search for a conceptual video). | H8: Apply StandardScaler and MinMaxScaler to a numerical column in the Titanic dataset and observe the changes.
D9: 3 | E9: Encoding Categorical Featues (One-Hot Encoding, Label Encoding) | F9: Gèron, Chapter 2 (section on categorical features). Scikit-learn OneHotEncoder and LabelEncoder documentation). | G9: "One-Hot Encoding vs. Label Encoding" (conceptual video). | H9: Apply LabelEncoder to a binary categorical column (e.g., 'Sex' in Titanic). Apply OneHotEncoder to a multi-class categorical column (e.g., 'Embarked' in Titanic).
D10: 4 | E10: Feature Engineering Introduction (Creating new features from existing ones) | F10: Towards Data Science: "A Comprehensive Guide to Feature Engineering" (skim for ideas). | G10: "Feature Engineering Explained" (conceptual video) | H10: On the Titanic dataset, create at least two new features (e.g., 'FamilySize' from "SibSp' and 'Parch', 'Title' from 'Name'.
D11: 5 | E11: Exploratory Data Analysis (EDA) Techniques (Histograms, scatter plots, correlation matrices, box plots). Practice: Apply preprocessing steps to a real-world dataset (e.g., Titanic, California Housing) and perform comprehensive EDA. | F11: A comprehensive EDA guide (e.g., from Kaggle Notebooks, Towards Data Science). | G11: "Comprehensive EDA in Python" (e.g., on YouTube, DataCamp). | H11: Perform a thorough EDA on the preprocessed Titanic dataset: Use corr() to see correlations. Create visualizations (histograms, box plots) to understand distributions and relationships between features and the 'Survived' target. | I11: Finalize preprocessing and EDA for the Titanic dataset.
A12: 3 | B12: Supervised Learning - Regression | C12: Understand linear regression and its principles | D12: 1 | E12: Introduction to Regression | F12: Gèron, Chapter 3: Classification (start with classification, but also covers regression intro conceptually). Ng ML Course: Week 1, "Linear Regression with One Variable". | G12: Ng ML Course: "What is Regression" lecture. | H12: Identify real-world problems that can be solved with regression.
D13: 2 | E13: Simple Linear Regression | F13: Gèron, Chapter 4: Training Models (Linear Regression section). | G13: Ng ML Course: "Cost Function" and "Gradient Descent". | H13: Derive the simple linear regression formula intuitively. Implement a simple linear regression from scratch using NumPy (gradient descent for one variable).
D14: 3 | E14: Multiple Linear Regression | F14: Gèron, Chapter 4 (Multiple Linear Regression). | G14: Ng ML Course: "Gradient Descent for Multiple Variables". | H14: Use Scikit-learn's LinearRegression on a simple synthetic dataset with multiple features. Interpret coefficients.
D15: 4 | E15: Model Evaluation for Regression | F15: Gèron, Chapter 2 (Evaluating models section). Scikit-learn documentation for MSE, RMSE, MAE, R2 score. | G15: "Regression Metrics Explained" (e.g., StatQuest - R-squared). | H15: Calculate MSE, RMSE, MAE, and R-squared for your Linear Regression model from yesterday.
D16: 5 | E16: Bias-Variance Tradeoff | F16: Gèron, Chapter 4 (Bias/Variance tradeoff section). Towards Data Science: "Bias-Variance Tradeoff Explained". | G16: StatQuest: "Bias and Variance". | H16: Reflect on how increasing model complexity can affect bias and variance. Draw a simple graph illustrating the tradeoff.
A17: 4 | B17: Supervised Learning - Classification I | C17: Grasp the fundamentals of classification with Logistic Regression and KNN | D17: 1 | E17: Introduction to Classification | F17: Gèron, Chapter 3 (Introduction to Classification) | G17: Ng ML Course: Week 3, "Classification" | H17: Identify real-world problems that can be solved with classification
D18: 2 | E18: Logistic Regression | F18: Gèron, Chapter 4 (Logistic Regression section). Scikit-learn LogisticRegression documentation. | G18: Ng ML Course: "Logistic Regression Model". StatQuest: "Logistic Regression". | H18: Implement Logistic Regression using Scikit-learn on theTitanic dataset (predicting 'Survived').
D19: 3 | E19: K-Nearest Neighbors (KNN) | F19: Gèron, Chapter 3 (KNN section). Scikit-learn KNeighborsClassifier documentation. | G19: StatQuest: "K-Nearest Neighbors" | H19: Implement KNN using Scikit-learn on the Titanic dataset. Experiment with different n_neighbors values.
D20: 4 | E20: Model Evaluation for Classification | F20: Gèron, Chapter 3 (Performance Measures section). Scikit-learn documentation for Confusion Matrix, Precision, Recall, F1-score, ROC AUC). | G20: StatQuest: "Confusion Matrix, Precision, Recall, F1-Score" and "ROC and AUC). | H20: For your Logistic Regression and KNN models on Titanic, calculate and interpret: Confusion Matrix, Precision, Recall, F1-score, and ROC AUC.
D21: 5 | E21: Introduction to Cross-Validation | F21: Gèron, Chapter 2 (Cross-Validation section). Scikit-learn cross_val_score documentation. | G21: "Cross Validation Explained" (e.g., from Google ML Crash Course, YouTube). | H21: Apply K-Fold Cross-Validation to your Logistic Regression and KNN models and compare the results to single train/test splits. | I21: Ensure your Titanic classification pipeline incorporates proper evaluation metrics and cross-validation
A22: 5 | B22: Supervised Learning - Decision Trees & Ensemble Methods I | C22: Learn about tree-based models and the concept of ensembling | D22: 1 | E22: Decision Trees | F22: Gèron, Chapter 6: Decision Trees. Scikit-learn DecisionTreeClassifier documentation. | G22: StatQuest: "Decision Trees". | H22: Implement a Decision Tree Classifier on the Titanic dataset. Visualize the tree (e.g., using plot_tree from Scikit-learn).
D23: 2 | E23: Overfitting in Decision Trees | F23: Gèron, Chapter 6 (Regularization Hyperparameters). | G23: "Overfitting and Underfitting in Decision Trees" (conceptual video). | H23: Experiment with max_depth and min_samples_leaf hyperparameters for for your Decision Tree and observe their effect on training and test accuracy (demonstrate overfitting).
D24: 3 | E24: Introduction to Ensemble Methods | F24: Gèron, Chapter 7: Ensemble Learning and Random Forests (Introduction) | G24: "Bagging vs. Boosting Explained" (conceptual video) | H24: Understand the difference between bagging (averaging/majority vote) and boosting (sequential correction).
D25: 4 | E25: Random Forests | F25: Gèron, Chapter 7 (Random Forest section). Scikit-learn RandomForestClassifier documentation. | G25: StatQuest: "Random Forests". | H25: Implement a Random Forest Classifier on the Titanic dataset. Compare its performance to a single Decision Tree.
D26: 5 | E26: Hyperparameter Tuning | F26: Gèron, Chapter 2 (Fine-tuning Your Model section). Scikit-learn GridSearchCV and RandomizedSearchCV documentation. | G26: "Grid Search and Random Search Explained". | H26: Apply GridSearchCV or RandomizedSearchCV to fine-tune the hyperparameters of your Random Forest model on Titanic. | I26: Apply Decision Trees and Random Forests to the chosen regression/classification project dataset. Perform hyperparameter tuning.
A27: 6 | B27: Supervised Learning - Ensemble Methods II & SVMs | C27: Dive deeper into boosting and introduce Support Vector Machines | D27: 1 | E27: Gradient Boosting Introduction | F27: Gèron, Chapter 7 (Gradient Boosting section). | G27: StatQuest: "Gradient Boosting Part 1". | H27: Understand the iterative nature of gradient boosting.
D28: 2 | E28: XGBoost/LightGBM | F28: High-level overview articles on XGBoost/LightGBM (e.g., from Towards Data Science). Don't get bogged down in internal details. | G28: "XGBoost Explained" (e.g., Krish Naik) | H28: Install xgboost or lightgbm. Implement an XGBoost classifier on the Titanic dataset. Compare its performance.
D29: 3 | E29: Support Vector Machines (SVMs) Introduction | F29: Gèron, Chapter 5: Support Vector Machines (Introduction) | G29: StatQuest: "Support Vector Machines Part 1". | H29: Understand the concept of the "maximal margin hyperplane".
D30: 4 | E30: Kernels in SVMs | F30: Gèron, Chapter 5 (Nonlinear SVM section). | G30: StatQuest: "Support Vector Machines Part 2 (Kernels)". | H30: Implement SVC (Support Vector Classifier) with different kernels (linear, RBF) on a classification dataset (e.g., Iris, or a subset of Titanic) and observe the decision boundaries.
D31: 5 | E31: Model Selection | F31: Revisit Gèron, Chapter 2 (End-to-End Projection section, thinking about model selection). | G31: "How to Choose the Right Machine Learning Model". | H31: Given a problem description, discuss which models you would initially consider and why. | I31: Experiment with XGBoost/LightGBM and SVMs on your project dataset. Reflect on which model performs best for your specific problem.
A32: 7 | B32: Unsupervised Learning - Clustering | C32: Understand how to group similar data points without labels | D32: 1 | E32: Introduction to Unsupervised Learning | F32: Gèron, Chapter 8, Unsupervised Learning Techniques (Introduction). | G32: Ng ML Course: Week 8, "Unsupervised Learning". | H32: Brainstorm real-world applications of unsupervised learning.
D33: 2 | E33: K-Means Clustering | F33: Gèron, Chapter 8 (K-Means section). Scikit-learn KMeans documentation. | G33: StatQuest: "K-Means Clustering". | H33: Implement K-Means on a synthetic dataset (e.g., make_blobs from Scikit-learn). Apply K-Means to a real dataset (e.g., Iris or Wine dataset) and try to interpret the clusters.
D34: 3 | E34: Elbow Method for K | F34: Articles on the Elbow method and Silhouette score. | G34: "Elbow Method for K-Means". | H34: Use the Elbow method to find an optimal k for a K-means clustering problem.
D35: 4 | E35: Hierarchical Clustering | F35: Gèron, Chapter 8 (Hierarchical Clustering, conceptually). Scikit-learn AgglomerativeClustering documentation. | G35: "Hierarchical Clustering Explained". | H35: Apply Hierarchical Clustering to a small dataset and visualize the dendrogram.
D36: 5 | E36: Clustering Evaluation Metrics & Applications | F36: Articles on Silhouette Score, adjusted Rand index (conceptual). | G36: "Clustering Evaluation Metrics". | H36: Calculate the Silhouette score for your K-Means results. Discuss real-world applications like customer segmentation or anomaly detection using clustering.
A37: 8 | B37: Unsupervised Learning - Dimensionality Reduction | C37: Learn techniques to reduce the number of features | D37: 1 | E37: Introduction to Dimensionality Reduction | F37: Gèron, Chapter 8 (Dimensionality Reduction Introduction). | G37: "Curse of Dimensionality Explained". | H37: Why is dimensionality reduction useful?
D38: 2 | E38: Principal Component Analysis (PCA) | F38: Gèron, Chapter 8 (PCA section). Scikit-learn PCA documentation. | G38: StatQuest: "PCA (Principal Component Analysis". | H38: Implement PCA on a dataset (e.g., MNIST digits, or Wine dataset) to reduce dimensions
D39: 3 | E39: Interpreting PCA Results | F39: Articles on on "explained variance ratio" and scree plots in PCA. | G39: "Interpreting PCA Results." | H39: Analyze the explained variance ratio from your PCA results to determine how many components to keep. Visualize the first two principal components.
D40: 4 | E40: Other Dimensionality Reduction Techniques (Conceptual) | F40: High-level overview of t-SNE, UMAP (focus on what they do, not deep math) | G40: "t-SNE Explained" (e.g., 3Blue1Brown's video). | H40: Understand when you might choose t-SNE over PCA.
D41: 5 | E41: Feature Selection vs. Feature Extraction | F41: Articles differentiating feature selection and feature extraction. | G41: "Feature Selection vs. Feature Extraction". | H41: Provide examples of both feature selection and feature extraction. | I41: Apply PCA to your project dataset if it has many features. Observe if it improves model performance or interpretability.
A42: 9 | B42: Neural Networks & Deep Learning I (Fundamentals) | C42: Grasp the basic concepts of neural networks | D42: 1 | E42: Introduction to Artificial Neural Networks | F42: Gèron, Chapter 10: Introduction to Artificial Neural Networks. | G42: Ng Deep Learning Specialization: Week 1, "Neural Network Basics" (or similar intro). 3Blue1Brown: "What is a Neural Network?" | H42: Draw a simple perceptron and understand its components.
D43: 2 | E43: Forward Propagation | F43: Gèron, Chapter 10 (Feedforward Network computations). | G43: "Forward Propagation Explained". | H43: Manually calculate the output of a simple 2-layer neural network given inputs and weights.
D44: 3 | E44: Backpropagation | F44: Gèron, Chapter 10 (Backpropagation section, focus on intuition). | G44: 3Blue1Brown: "Backpropagation" (highly recommended for intuition). | H44: Understand the concept of how errors are propagated backward to update weights.
D45: 4 | E45: Gradient Descent and Optimizers | F45: Gèron, Chapter 11: Training Deep Neural Networks (Optimizers section). | G45: Ng Deep Learning Specialization: Week 2, "Optimization Algorithms". StatQuest: "Stochastic Gradient Descent", "Adam Optimizers". | H45: Briefly explain why different optimizers (e.g., Adam vs. SGD) are used.
D46: 5 | E46: Overfitting in NNs (Regularization, Dropout) | F46: Gèron, Chapter 11 (Regularization sections). | G46: "Dropout Explained", "L1, L2 Regularization for Neural Networks". | H46: Identify techniques to combat overfitting in neural networks. | I46: Implement a simple feedforward neural network (MLPClassifier) using Scikit-learn for a classification problem (e.g., MNIST digits if you're feeling ambitious, or Iris).
A47: 10 | B47: Neural Networks & Deep Learning II (Frameworks & Architectures) | C47: Get hands-on with a deep learning framework and common architectures | D47: 1 | E47: Introduction to Deep Learning Frameworks (TensorFlow/Keras or PyTorch) | F47: Keras or PyTorch official "getting started" guides | G47: "TensorFlow/Keras for Beginners" or "PyTorch for Beginners" (e.g., from freeCodeCamp, DataCamp, or official tutorials). Choose one framework to focus on. | H47: Install your chosen framework. Run a simple "Hello World" or basic tensor operation.
D48: 2 | E48: Building a Simple Neural Network with Keras/PyTorch (Regression) | F48: Keras/PyTorch sequential model documentation (for building a simple MLP). | G48: Tutorial on building a basic regression NN. | H48: Build and train a simple MLP for a regression problem (e.g., Boston Housing dataset).
D49: 3 | E49: Building a Simple Neural Network with Keras/PyTorch (Classification) | F49: Keras/PyTorch classification model documentation | G49: Tutorial on building a basic classification NN. | H49: Build and train a simple MLP for a classification problem (e.g., Fashion MNIST or a simple binary classification).
D50: 4 | E50: Introduction to Convolutional Neural Networks (CNNs) | F50: Gèron, Chapter 14: Convolutional Neural Networks (Introduction). | G50: Ng Deep Learning Specialization: Week 1, "Convolutional Neural Networks". StatQuest: "Convolutional Neural Networks". | H50: Understand the concept of convolution, pooling, and how CNNs excel at image data.
D51: 5 | E51: Transfer Learning | F51: Gèron, Chapter 11 (Transfer Learning section) | G51: "Transfer Learning Explained". | H51: Understand the concept of using pre-trained models. | I51: Apply your chosen deep learning framework to your project. If it's image data, consider a simple CNN. If not, refine your MLP.
A52: 11 | B52: Model Development & MLOps Basics | C52: Understand how ML models are used in real-world applications | D52: 1 | E52: Model Saving and Loading | F52: Scikit-learn joblib / pickle documentation. Keras/PyTorch model saving documentation. | G52: "Saving and Loading ML Models". | H52: Train a simple Scikit-learn model, save it, and then load it to make a prediction.
D53: 2 | E53: Basic API Endpoints for Models | F53: Flask or FastAPI "getting started" tutorial for a simple API. | G53: "Deploying a Scikit-learn Model with Flask/FastAPI" (search for tutorials) | H53: Create a very basic Flask/FastAPI app that loads your saved model and makes predictions via an API endpoints.
D54: 3 | E54: Introduction to MLOps | F54: MLOps lifecycle overview articles (e.g., from Google Cloud, IBM). | G54: "What is MLOps?" (conceptual video) | H54: List the key stages in MLOps lifecycle and why each is important.
D55: 4 | E55: Model Monitoring | F55: Articles on concept drift, data drift, and model performance monitoring. | G55: "Model Monitoring in Production". | H55: Think about metrics you would monitor for a deployed regression model and a classification model. How wouldyou deetect drift?
D56: 5 | E56: A/B Testing for ML Models | F56: Articles on A/B testing best practices for ML | G56: "A/B Testing Machine Learning Models". | H56: Design a simple A/B test for two different versions of a recommendation model. | I56: Consider how you would save/load yoru project's model. Think about hypothetical deployment scenarios and what metrics you'd monitor.
A57: 12 | B57: Capstone Project & Review | C57: Consolidate knowledge by working on a complete project and review | D57: 1 | E57: Capstone Project | F57: Use all resources from previous weeks as needed. Kaggle competition notebooks are excellent for seeing how others approach problems. | G57: Refer back to specific tutorials as you implement different steps. | H57: Focus entirely on your chosen project. Refine problem definition, finalize data collection/preprocessing strategy.
D58: 2 | H58: Experiment with 2-3 different models (from different categories, e.g., Logistic Regression, Random Forest, simple NN).
D59: 3 | H59: Tune hyperparameters, evaluate models thoroughly using appropriate metrics and cross-validation. Select the best performing model.
D60: 4 | H60: Perform error analysis. What did the model get wrong? Why? Can you improve it with more feature engineering or different models?
D61: 5 | E61: Review all core concepts | F61: Skim through Gèron's book or your notes, highlighting key concepts. | G61: Re-watch any StatQuest or Ng ML Course videos on topics you found challenging. | H61: Create flashcards for key terms and algorithms. Draw diagrams of complex concepts (e.g., how a neural network works, the flow of data in a pipeline). Attempt to explain a complex ML concept to an imaginary non-technical person. This is a great way to solidify understanding. Identify areas you still feel weak in and make a plan for continued learning.

Sheet ML System Design
A1: Week | B1: Theme | C1: Unit | D1: Topic | E1: Reading | F1: Reading | G1: Reading | H1: Video | I1: Video | J1: Video | K1: Exercise (Scenario) | L1: Exercise (Tasks) | M1: Date | N1: Progress | O1: Key Resources
A2: 1 | B2: Foundations of ML Design | C2: 1 | D2: Introduction & Frameworks | E2: "Machine Learning System Design Interview" by Chip Huyen (intro section on interview goals and structure) | F2: Machine Learning System Design Interview (2025 Guide) | H2: This ML Design Interview Strategy Got Me Into Meta | K2: Outline your own preferred 5-7 step framework for ML system design interviews on paper or a whiteboard. Think about why each step is important. | O2: Machine Learning System Design Interview by Chip Huyen
C3: 2 | D3: Problem Definition & Metrics | E3: "Metrics for Machine Learning" (Google Developers ML Crash Course, focus on classification/regression metrics) | F3: "Evaluation Metrics for Recommender Systems" (revisit later, but get a high-level oveerview of different problem types). Skim for different types like Ranking, Rating). | H3: "Machine Learning Metrics (Accuracy, Precision, Recall, F1, ROC AUC)" (StatQuest with Josh Starmer) | K3: You need to design a system to detect fraudulent credit card transactions.prioritize and why (e.g., high precision to avoid false accusations, or high recall to catch all fraud)? (d) Discus the trade-offs beetween different metrics in this context. | L3: (a) How would you define this as an ML problem (classification, regression, etc.)? (b) What are the business goals? (c) What ML metrics would you prioritize and why (e.g., high precision to avoid false accusations, or high recall to catch all fraud)? (d) Discus the trade-offs beetween different metrics in this context.
C4: 3 | D4: Data Strategy | E4: "The Unreasonable Effectiveness of Data" by Alon Halevy, Peter Norvig, Fernando Pereira (classic paper on data's importance). Focus on the data-centric view. | F4: "Challenges in Data Collection and Preparation for Machine Learning" (search for a good blog post, e.g., on Medium, covering data cleaning, missing values, etc). | H4: "Data Collection for Machine Learning" (A high-level overview, search YouTube for "ML data collection pipeline"). Focus on the journey of raw data to usable data. | K4: You're building a system to recommend news articles to users. | L4: (a) What types of data would you need to collect (user data, article data, interaction data)? (b) How would you collect this data (logs, explicit feedback, external sources)? (c) What are potential data quality issues you might encounter (missing user profiles, outdated articles, bot activity)? (d) How would you address data bias (e.g., only showing popular articles, reinforcing existing views)?
C5: 4 | D5: Feature Engineering | E5: "Feature Engineering for Machine Learning" (a good general overview blog post, e.g., on Towards Data Science or Medium). | F5: "Embeddings: The Secret Sauce of ML" (Google Developers ML Crash Course). Read the text section. | H5: "Feature Engineering for Machine Learning - Data Science Crash Course" (freeCodeCamp.org). Focus on the concepts, not the code. | K5: You're improving a housing price prediction model. | L5: (a) List 5-7 raw features you'd consisder (e.g., square footage, number of bedrooms, location). (b) For each, propose 1-2 engineered features (e.g., "square footage per bedroom", "distance to nearest school/hospital", "age of house", "one-hot encode location/neighborhood"). (c) Briefly explain why each engineered feature might be useful.
C6: 5 | D6: Model Selection & Training | E6: "Choosing the right machine learning model" (IBM blog or similar, focus on high-level decision factors like data size, interpretability, performance). | F6: "Generalization: Overfitting and Underfitting" (Google Developers ML Crash Course). | H6: "Machine Learning Basics: Training and Testing" (Google Developers) | I6: "Cross Validation Explained" (StatQuest with Josh Starmer) | K6: You've built a classification model for detecting spam emails. | L6: (a) Explain the concept of overfitting and underfitting in this context. (b) How would you split your data for training, validation, and testing? Why this split? (c) What techniques wouldd you use to prevent overfitting (e.g., regularization, more data, feature selection)? (d) If your model performs very well on the training data but poorly on unseen data, what would you suspect, and what would be your next steps?
A7: 2 | B7: System Architecture & Scalability | C7: 1 | D7: High-Level Architecture | E7: "System Design Primer - Introduction to system design" (general primer, focus on core components like load balancers, databases, caching, message queues). Skim relevant sections. | F7: "ML System Architecture - A General Framework" (search for blog posts that break down an ML system into ingestion, training, serving, monitoring components). | H7: "System Design Interview Crash Course - Introduction" (freeCodeCamp.org - focus on the component breakdown). Watch first 15-20 min. | K7: Design a high-level architecture for an online movie recommendation system (like Netflix). | L7: (a) Identify the main components (e.g., data ingestion, user profiles, movie catalog, recommendation engine, serving layer). (b) Draw a block diagram showing how these components interact. (c) Briefly describe the purpose of each component.
C8: 2 | D8: Scalability & Distributed Systems | E8: "Scalability - System Design Prmer" (focus on horizontal vs. vertical scaling, load balancing). | F8: "Introduction to Apache Kafka" (Confluent blog or similar, understand its role as a distributed log/message queue). | H8: "Distributed Systems in One Lesson" (Advanced Concepts in Operating Systems). Focus on key challenges and concepts like consistency. | I8: "What is Apache Spark?" (brief introductory video). | K8: Your recommendation system becomes wildly popular and experiences massive traffic spikes. | L8: (a) How would you scale your data ingestion pipeline? (Think Kafka, distributed processing). (b) How would you scale your model training process? (Think Spark, distributed computing). (c) How would you scale your model serving component to handle millions of requests per second? (Think load balancing, multiple instances).
C9: 3 | D9: Data Storage for ML | E9: "SQL vs. NoSQL Databases: What's the difference? (general overview) | F9: "What is a Data Lake? What is a Data Warehouse?" (brief comparison) | G9: "What is a Feature Store?" (brief intro, e.g., from Tecton or Feast documentation). | H9: "Data Lake vs Data Warehouse" (quick explainer). | I9: "What is a Feature Store? And why you need one for Machine Learning" (Snorkel AI). Watch the first 10-15 min. | K9: You are designing a system for real-time fraud detection. | L9: (a) Where would you store historical raw transaction data (for batch training/analysis)? (b) Where would you store features needed for real-time inference (e.g., user's recent transactio history, IP addresses)? (c) Would you use a SQL or NoSQL database for real-time feature lookups, and why? (d) Consider the benefits of a feature store in this scenario.
C10: 4 | D10: Model Deployment & Serving | E10: "Model Serving: The Last Mile in ML" (a blog post on different serving patterns: batch, online, streaming). | F10: "Dockerizing a Machine Learning Model" (brief intro to Docker for ML). | G10: "Kubernetes for ML Model Deployment" (brief intro to Kubernetes concepts). Skim the "What is Kubernetes?" and "Components" sections. | H10: "Online vs. Offline Machine Learning" (explainer video). | I10: "What is Docker?" (brief explainer) | J10: "What is Kubernetes?" (brief explainer) | K10: You have trained a computer vision model to classify images as "cat" or "dog", and you need to deploy it for an online web application. | L10: (a) Would you use online or offline inference? Why? (b) Describe the API endpoint your model serving layer would expose. What inputs and outputs would it expect? (c) How would you ensure low latency for image classification requests? (d) Explain how Docker and Kubernetes could help in deploying and managing this model.
C11: 5 | D11: Monitoring & MLOps | E11: "Monitoring Machine Learning Models in Production" (e.g., a blog post from a platform like Arize, WhyLabs, or Datadog). | F11: "Data Drift and Concept Drift in Machine Learning" (explanation of these phenomena). | H11: "MLOps explained in 10 minutes" (Google Cloud Tech). | I11: "Data Drift vs Concept Drift)" (quick explainer) | K11: Your deployed spam detection model (from Tuesday, Week 1) is showing a decrease in performance. | L11: (a) What metrics would you monitor on the model's performancee (e.g., accuracy, precision, recall over time)? (b) What data-related metrics woudl you monitor to detect potential issues (e.g., input feature distributions, changes in email content)? (c) How would you set up alerts for these merics? (d) If you detect concept drift (e.g., spammers change their tactics), what would be your retraining strategy?
A12: 3 | B12: Advanced Topics & Case Studies | C12: 1 | D12: Recommendation Systems | E12: "Recommender Systems: An Introduction" (skim relevant chapters, or find a good blog series on collaborativfe filtering, content-based, hybrid). This source is academic, so maybe find a good summary article. | F12: "Netflix Recommendations: Beyond the 5 stars (A look at the algorithm)" (classic blog post). | H12: "Recommender Systems Explained" (freeCodeCamp.org). Focus on types of recommenders. | K12: Design a "Next Product to Buy" recommendation system for an e-commerce website. | L12: (a) What are the primary types of data you'd use? (b) Would you lean towards collaborative filtering, content-based, or a hybrid approach? Why? (c) How would you handle cold-start problems for new users or new products? (d) What evaluation metrics are crucial for this system?
C13: 2 | D13: Search Systems / Ranking | E13: "Introduction to Information Retrieval" (Stanford textbook, read relevant chapters on "Scoring, Term Weighting and the Vector Space Model" and "Evaluation in Information Retrieval"). | F13: "How Google Search Works" (official Google explanation or an explanatory blog post). | H13: "Lecture 1: Introduction to Information Retrieval" (Stanford CS276). Watch first 20-30 min for context. | K13: Design the search engine for an internal company wiki. | L13: (a) How would you define document releance? (b) What features would you use to rank search results (e.g., keyword matching, page authority, recency, user clicks)? (c) How would you handle misspellings or synonyms in user queries? (d) What would be the primary challenges in scaling such a system?
C14: 3 | D14: Fraud Detection / Anomaly Detection | E14: "Anomaly Detection: A Survey" (find a good survey paper or blog that explains different types of anomaly detection techinques: statistical, ML-based, etc.). | F14: "Handling Imbalanced Datasets for Fraud Detection" (blog post, focus on techniques like oversampling, undersampling, SMOTE, cost-sensitive learning). | H14: "What is Anomaly Detection?" (brief explainer). | I14: "Handling Imbalanced Data" (quick overview of techniques). Search for a good one, many available. | K14: Design a system to detect unusual login attempts for a financial institution. | L14: (a) What features would indicate an anomalous login (e.g., location changes, device changes, time of day, frequency)? (b) How would you handle the highly imbalanced nature of login data (most are legitimate)? (c) Would you prioritize precision or recall for this system? Justify your choice. (d) Describe the real-time vs. batch aspects of such a system.
C15: 4 | D15: Real-time ML / Low-Latency Systems | E15: "Real-time Machine Learning Systems: A Survey" (find a concise survey or blog post on the topic). | F15: "Stream Processing vs. Batch Processing" (explainer). | H15: "Real-time ML Systems - Design Patterns" (e.g., from an industry conference talk on YouTube, search for "real-time ML system design). Focus on the architectural patterns. | K15: Design a dynamic pricing system for a ride-sharing app (like Uber's surge pricing). | L15: (a) What data would you need in real-time to make pricing decisions (e.g., current demand, available drivers, historical patterns)? (b) Describe the real-time data pipeline required to feed features to your model. (c) What are the latencyc requirements for this system, and how would you achieve them? (d) How would you handle immediate feedback loops (e.g., price changes affecting demand instantly)?
C16: 5 | D16: Practice Case Study | E16: None for today, focus on synthesis | H16: None for today | K16: Design a news feed ranking system (like Facebook's or LinkedIn's). | L16: (a) Time allocation: Spend 5-10 minutes clarifying requirements and scope. 15-20 minutes on data and features. 10-15 minutes on model selection and training. 10-15 minutes on system architecture (online/offlline, serving, storage). 5-10 minutes on evaluation, monitoring, and future improvements. (b) Verbalize: Speak your thoughts out loud as if in an interview. Explain your choices and trade-offs. (c) Self-Critique: After the hour, review your own design. Did you cover all framework steps? Were your explanations clear? Did you consider edge cases or trade-offs?
A17: 4 | B17: Deep Dive & Mock Interviews | C17: 1 | D17: System Design Principles | E17: "CAP Theorem Explained" (e.g., from Martin Fowler or a good distributed systems blog). | F17: "ACID vs BASE" (explainer) | H17: "CAP Theorem" (Gaurav Sen) | I17: "ACID vs BASE in Databases" (brief explainer) | K17: You need to choose a database for a real-time leaderboard in a gaming app. | L17: (a) Which CAP theorem properties would you prioritize (Consistency, Availabilty, Partition Tolerance)? Why? (b) Would you lean towards an ACID-compliant database or a BASE-compliant one? (c) Discuss the rade-offs in your choice regarding data integrity vs. user experience/speed.
C18: 2 | D18: Common Pitfalls & Anti-Patterns | E18: Search for "common mistakes in ML system design interviews" or "ML system design anti-patterns". | F18: "Don't Over-Engineer Your ML System" (a blog post discusing the balance between simplicity and complexity). | H18: "Top 5 Mistakes in ML System Design Interviews" (search for a video that covers this, many exist). | K18: You hear a candidate proposing a very complex, cutting-edge deep learning model for a simple tabular classification problem with limited data. | L18: (a) Identify the potential pitfalls in this approach. (b) How would you politely guide the candidate towards a more suitable solution? (c) Think about other common anti-patterns (e.g., ignoring monitoring, not considering data bias, jumping straight to a solution).
C19: 3 | D19: Behavioral Aspects & Communication | E19: "How to ACE the ML System Design Interview: Communication and Soft Skills" (search for articles on this topic. | F19: "STAR Method for Behavioral Interviews" (brief refresher) | H19: None | K19: The interviewer asks a very vague question like "Design an AI system". | L19: (a) Practice asking clarifying questions. What would you ask to narrow down the scope, understand the business goal, and define the ML problem? (b) Practice articulating trade-offs clearly and concisely (e.g., "We could use a more complex model for higher accuracy, but this woudl increase latency and computational cost. Given our latency requirement of X, I propose starting with a simpler model...".
C20: 4 | D20: Mock Interview | E20: None | K20: Goal: Simulate a real interview. Find a Partner: This is crucial. Find a friend, colleague, or use platforms like Pramp or interviewing.io (though paid) for a peer mock interview. | L20: Question: Have your partner give you a common ML system design question (e.g., "Design a spam detector", "Design a product search system", "Design a ride-sharing price surge system"). Execute: Go through your framework, explaining your thought process out loud. Feedback: Ask your partner for honest, constructive feedback on: (a) Clarity of communication (b) Completeness of your design (c) Identification of tradeoffs (d) Ability to handle follow-up questions (e) Structure of your answer.
C21: 5 | D21: Review & Refine | E21: Re-read sections based on mock interview feedback | H21: Re-watch videos on areas identified as weak | L21: Reflect: Take detailed notes on the feedback from your mock interview. Targeted Study: Pick 1-2 specific areas where you struggled (e.g., explaining data partitioning, justifying model choice, defining evaluation metrics). Spend time reviewing just those topics. Iterate on Framework: Does your framework need adjustment? Were there steps you consistently missed or rushed? Practice Short Answers: For follow-up questions, practice giving concise, confident answers. Future Planning: Plan for another mock interview soon.

Sheet Transformers
A1: Week | B1: Theme | C1: Unit | D1: Topic | E1: Concept | F1: Reading | G1: Video | H1: Exercise | I1: Project | J1: Date | K1: Progress | L1: Key Resources | M1: Notes
A2: 1 | B2: Introduction to Attention | C2: 1 | D2: The Bottleneck of RNNs/LSTMs & The Need for Attention | E2: Briefly revisit the limitations of vanilla RNNs/LSTMs in handling long sequences (vanishing/exploding gradients, information bottleneck in fixed-size context vectors). Introduce the idea that models need to "focus" on relevant parts of the input. | F2: "Attention Is All You Need" (skim introduction and background sections for motivation) | G2: "Sequence to Sequence with Attention" by Google Developers (or similar introductory video) | H2: (Mental) Imagine translating a very long sentence. How would a human do it versus a simple sequence-to-sequence model without attention? | L2: "Attention Is All You Need" by Vaswani et al. (2017) | M2: Strategy: Read in stages as suggested in the daily breakdown. Don't feel pressured to understand every mathematical detail on the first pass. Focus on the high-level ideas first.
C3: 2 | D3: The Core Idea of Attention - Query, Key, Value | E3: Introduce the abstract concept of Query, Key, and Value vectors as the foundation of attention. Explain their roles: Query (what I'm looking for), Key (what I have), Value (the information associated with what I have). | F3: Blog posts explaining Q, K, V (e.g., "The Illustrated Transformer" by Jay Alammar - focus on the attention part) | G3: "Attention Mechanism Explained" (Look for videos that visually explain Q, K, V interactions). | L3: "The Illustrated Transformer" by Jay Alammar | M3: An absolute must-read for visual learners. It breaks down complex concepts into easily digestible diagrams. Other blog posts from Towards Data Science, Analytics Vidhya, etc., explaining specific components.
C4: 3 | D4: Dot-Product Attention - The Math Behind the Focus | E4: Deep dive into the mechanics of scaled dot-product attention. Explain how the dot product measures similarity between Query and Key, scaling for stability, and applying soft max to get attention weights. Then, how these weights are used to take a weighted sum of the Values to form the context vector. | F4: "Attention Is All You Need" (Section 3.2 - Scaled Dot-Product Attention). Practical blog posts with code snippets for dot-product attention. | G4: "Neural Machine Translation with Attention" (focus on the attention scoring and weighted sum). | H4: Work through a small example of calculating dot-product attention manually with simple vectors. | L4: StatQuest with Josh Starmer | M4: Often provides intuitive explanations of machine learning concepts, including some relevant to attention.
C5: 4 | D5: Visualizing Attention | E5: Understand how attention weights are distributed. Visualize attention maps (e.g., heatmaps showing which input words are attended to for each output word). | F5: "The Illustrated Transformer" by Jay Alammar (focus on the visual explanations of attention). | G5: Videos or interactive demos showcasing attention heatmaps in machine translation or text summarization. | I5: (Mini) Find an existing attention visualization tool online (e.g., within a Hugging Face library demo) and experiment with it. | L5: 3Blue1Brown | M5: While not specific to Transformers, his neural network videos provide excellent mathematical intuition that is foundational.
C6: 5 | D6: Additive and Multiplicative Attention (Briefly) | E6: Briefly touch upon the historical context and different forms of attention (additive/concatenative vs. multiplicative/dot-product attention), emphasizing that dot-product attention is prevalent in Transformers. | F6: A short article comparing additive and multiplicative attention. | G6: A quick overview of different attention types. | L6: DeepLearning.ai | M6: Coursera courses (e.g., "Natural Language Processing with Attention Moddels", "Attention Mechanisms and Transformer Models") offer structure video lectures.
C7: 6 | D7: Review and Q&A - Attention Fundamentals | E7: Consolidate understanding of attention mechanisms. Review Q, K, V, don't-product attention, and its purpose. | F7: Re-read key sections from the week. | H7: Solve a few conceptual questions about attention mechanisms. | L7: Google Developers | M7: Often release introductory videos on new architectures.
A8: 2 | B8: Deep Dive into Self-Attention and Multi-Head Attention | C8: 1 | D8: Self-Attention Explained | E8: Introduce self-attention, where Q, K, V come from the same input sequence. Explain why this is powerful for understanding internal relationships within a sequence. | F8: "The Illustrated Transformer" (Self-Attention section). | G8: Videos specifically explaining self-attention with examples (e.g., "The animal didn't cross the street because it was too tired" - what "it" refers to). | H8: Trace the self-attention process for a short sentence: how a word's representation is influenced by other words in the same sentence.
C9: 2 | D9: Multi-Head Attention - Why Multiple Heads? | E9: Explain the motivation behind multi-head attention: allowing the model to attend to different "aspects" or relationships simultaneously. Analogy: multiple "filters" or "lenses". | F9: "Attention Is All You Need" (Section 3.2.2 - Multi-Head Attention). Blog posts providing intuition for multiple heads. | G9: Videos explaining multi-head attention visually.
C10: 3 | D10: Multi-Head Attention - The Mechanics | E10: Dive into the detailed steps: linear projections for each head, parallel attention calculations, concatenation of outputs, and a final linear projections. Discuss the dimensionality reduction per head. | F10: "The Illustrated Transformer" (Multi-Head Attention section). | G10: Step-by-step breakdown of multi-head attention calculation. | H10: Draw a diagram of the multi-head attention process with input dimensions and output dimensions.
C11: 4 | D11: Implementing Self-Attenetion (Conceptual/Pseudocode) | E11: Walk through the pseudocode or conceptual implementation of a self-attention layer. Focus on matrix multiplications. | F11: Python/PyTorch/TensorFlow tutorials on implementing self-attention from scratch (don't need to run code yet, just understand the structure). | G11: Write down the mathematical operations (matrix multiplications) for a self-attention calculation.
C12: 5 | D12: Implementing Multi-Head Attention (Conceptual/Pseudocode) | E12: Extend the previous day's understanding to multi-head attention implementation. Highlight the parallel nature and the final concatenation. | F12: Python/PyTorch/TensorFlow tutorials on implementing multi-head attention. | H12: Modify your self-attention pseudocode to include multiple heads.
C13: 6 | D13: Advantages and Disadvanges or Attention | E13: Summarize the benefits (parallelization, long-range dependencies, interpretability) and potential drawbacks (computational cost for very long sequences, quadratic complexity of self-attention). | F13: Articles discussing the pros and cons of attention and Transformers. | G13: Videos contrasting RNNs with Attention models.
A14: 3 | B14: The Transformer Architecture - Encoder | C14: 1 | D14: Introduction to the Transformer Architecture | E14: Overview of the "Attention Is All You Need" paper and its revolutionary nature. Introduce the encoder-decoder structure of the original Transformer. | F14: Re-read the abstract and introduction of "Attention Is All You Need". | G14: High-level overview videos of the Transformer architecture.
C15: 2 | D15: Positional Encoding - Adding Order to Chaos | E15: Explain why positional encoding is vital (Transformers don't have inherent sequence order like RNNs). Dive into the sinusoidal positional encoding from the original paper - why sine/cosine, and how it encodes relative and absolute positions. | F15: "Attention Is All You Need" (Section 3.5 - Positional Encoding). Blog posts on positional encoding. | G15: Visual explanations of positional encoding. | H15: Understand how adding positional encodings to word embedding works conceptually.
C16: 3 | D16: Encoder Block: Multi-Head Self-Attention in Context | E16: Place the multi-head self-attention layer within the encoder block. Explain how the output of one layer feeds into the next. | F16: "The Illustrated Transformer" (Encoder section). | G16: Videos breaking down the encoder block.
C17: 4 | D17: Encoder Block: Feed-Forward Networks | E17: Explain the role of the position-wise feed-forward network in the encoder. It's a simple, fully connected network applied independently to each position. | F17: "Attention Is All You Need" (Section 3.3 - Position-wise Feed-Forward Networks). | G17: Short explanations of feed-forward networks in Transformers.
C18: 5 | D18: Encoder Block: Add & Norm (Residual Connections and Layer Normalization) | E18: Explain the purpose of residual connections (skip connections) for gradient flow and layer normalization for stabilizing training. | F18: Articles on Residual Connections and Layer Normalization in deep learning. | G18: Explanations of "Add & Norm". | H18: Consider why residual connections are important for deep networks.
C19: 6 | D19: Putting the Encoder Together | E19: Review all components of the encoder bock and how they work in sequence. Discuss the stacking of multiple encoder layers. | F19: Comprehensive diagrams/explanations of the full encoder stack. | G19: Animations or walkthroughs of the data flow through an encoder. | H19: (Mini) Sketch out the full encoder architecture, labeling all components and data flow.
A20: 4 | B20: The Transformer Architecture - Decoder and Applications | C20: 1 | D20: Decoder Block - Masked Multi-Head Self-Attention | E20: Introduce the decoder block. Explain why masked self-attention is necessary in the decoder (to prevent attending to the future tokens during sequence generation). | F20: "Attention Is All You Need" (Section 3.4 - Decoder). "The Illustrated Transformer" (Decoder section). | G20: Explanation of masked self-attention.
C21: 2 | D21: Decoder Block - Encoder-Decoder Attention (Cross-Attention) | E21: Explain the second attention mechanism in the decoder, where the Queries come from the decoder's previous layer, and Keys/Values come from the encoder's output. This allows the decoder to "look at" the source sequence. | F21: "Attention Is All You Need" (Section 3.4 - Encoder-Decoder Attention). | G21: Visuals showing cross-attention between encoder and decoder outputs. | H21: Compare the Q, K, V, sources for masked self-attention and encoder-decoder attention.
C22: 3 | D22: The Full Transform: Encoder + Decoder | E22: Integrate all components to understand the complete Transform architecture for sequence-to-sequence tasks (like machine translation). Discuss the training process. | F22: Comprehensive walkthroughs of the entire Transform model. | G22: Full animations or step-by-step explanations of the Transformer.
C23: 4 | D23: Applications: Machine Translation & Text Summarization | E23: Discuss how the Transformer is applied to these tasks. Why it excels compared to previous models. | F23: Case studies or articles on Transformer applications in NLP. | G23: Demos of Transformer-based machine translation or summarization.
C24: 5 | D24: Applications: Large Language Models (LLMs - BERT, GPT) | E24: Introduce the concept of pre-training and fine-tuning. Briefly explain BERT (encoder-only) for understanding, and GTP (decoder-only) for generation. | F24: High-level overviews of BERT and GTP architectures. | G24: Explanations of how LLMs leverage the Transformer.
C25: 6 | D25: Practical Considerations & Further Learning | E25: Briefly discuss computational efficiency, training challenges, and innovations beyond the original Transformer (e.g., Reformer, Performer for efficiency; T5, GLM for different pre-training objectives). | F25: Articles on Transformer variations and the future of the architecture. | G25: Talks or lectures on advanced Transformers topics.
C26: 7 | D26: Review and Future Directions | E26: Consolidate all knowledge. Discuss open problems and future research directions in attention and Transformers. | H26: Attempt to explain the entire Transformer architecture to an imaginary peer.
A27: 5 | C27: 1
C28: 2
C29: 3
C30: 4
C31: 5
A32: 6 | C32: 1
C33: 2
C34: 3
C35: 4
C36: 5
A37: 7 | C37: 1
C38: 2
C39: 3
C40: 4
C41: 5
A42: 8 | C42: 1
C43: 2
C44: 3
C45: 4
C46: 5
A47: 9 | C47: 1
C48: 2
C49: 3
C50: 4
C51: 5
A52: 10 | C52: 1
C53: 2
C54: 3
C55: 4
C56: 5
A57: 11 | C57: 1
C58: 2
C59: 3
C60: 4
C61: 5
A62: 12 | C62: 1
C63: 2
C64: 3
C65: 4
C66: 5

Sheet RAGFine Tuning
A1: Week | B1: Goal | C1: Unit | D1: Topic | E1: Reading | F1: Reading | G1: Video | H1: Video | I1: Exercise | J1: Project | K1: Date | L1: Progress | M1: Key Resources
A2: 1 | B2: Introduction to LLMs and the Need for Augmentation | C2: 1 | D2: What are LLMs? | E2: "What are Large Language Models (LLMs)?" (IBM or Elastic resources are good starting points). Focus on their architecture (briefly mention Transformers), pre-training, and common applications. | F2: "An intuitive guide to Large Language Models" (search for a blog post or article that explains it simply). | G2: "A Gentle Introduction to Large Language Models (LLMs)" (look for a beginner-friendly YouTube video, e.g., from freeCodeCamp or a similar educational channel). | H2: Short explainer video on the Transformer architecture (e.g., "The Illustrated Transformer" by Jay Alammar - focus on the high-level idea, not every mathematical detail). | I2: Experiment with a publicly available LLM (e.g., ChatGPT, Gemini, or a free tier of a commercial API like OpenAI's playground). Ask it questions about recent events (post its knowledge cutoff) and observe its limitations. Ask it factual questions and try to spot potential "hallucinations". | M2: "Hands-On Machine Learning with Scikit-Learn, Keras, and TensorFlow" by Aurèlien Gèron (2nd or 3rd Edition): This book is a goldminefor practical examples and theoretical understanding. We'll refer to it as "Gèron" for brevity.
C3: 2 | M3: Andrew Ng's Machine Learning Specialization (Coursera): Excellent for foundational understanding. We'll refer to it as "Ng ML Course".
C4: 3 | M4: Scikit-learn documentation: Official documentation is invaluable.
C5: 4 | M5: Kaggle: For datasets and practice competitions.
C6: 5 | M6: Google Colab/Jupyter Notebooks: For coding
A7: 2 | C7: 1
C8: 2 | D8: https://g.co/gemini/share/28e7ac488163
C9: 3
C10: 4
C11: 5
A12: 3 | C12: 1
C13: 2
C14: 3
C15: 4
C16: 5
A17: 4 | C17: 1
C18: 2
C19: 3
C20: 4
C21: 5
A22: 5 | C22: 1
C23: 2
C24: 3
C25: 4
C26: 5
A27: 6 | C27: 1
C28: 2
C29: 3
C30: 4
C31: 5
A32: 7 | C32: 1
C33: 2
C34: 3
C35: 4
C36: 5
A37: 8 | C37: 1
C38: 2
C39: 3
C40: 4
C41: 5
A42: 9 | C42: 1
C43: 2
C44: 3
C45: 4
C46: 5
A47: 10 | C47: 1
C48: 2
C49: 3
C50: 4
C51: 5
A52: 11 | C52: 1
C53: 2
C54: 3
C55: 4
C56: 5
A57: 12 | C57: 1
C58: 2
C59: 3
C60: 4
C61: 5

Sheet AI Agents
A1: Week | B1: Theme | C1: Goal | D1: Unit | E1: Topic | F1: Reading | G1: Video | H1: Exercise | I1: Project | J1: Key Resources
A2: 1 | D2: 1 | E2: https://g.co/gemini/share/21a0c4088593
D3: 2
D4: 3
D5: 4
D6: 5
A7: 2 | D7: 1
D8: 2
D9: 3
D10: 4
D11: 5
A12: 3 | D12: 1
D13: 2
D14: 3
D15: 4
D16: 5
A17: 4 | D17: 1
D18: 2
D19: 3
D20: 4
D21: 5
A22: 5 | D22: 1
D23: 2
D24: 3
D25: 4
D26: 5
A27: 6 | D27: 1
D28: 2
D29: 3
D30: 4
D31: 5
A32: 7 | D32: 1
D33: 2
D34: 3
D35: 4
D36: 5
A37: 8 | D37: 1
D38: 2
D39: 3
D40: 4
D41: 5
A42: 9 | D42: 1
D43: 2
D44: 3
D45: 4
D46: 5
A47: 10 | D47: 1
D48: 2
D49: 3
D50: 4
D51: 5
A52: 11 | D52: 1
D53: 2
D54: 3
D55: 4
D56: 5
A57: 12 | D57: 1
D58: 2
D59: 3
D60: 4
D61: 5

Sheet SE System Design
A1: Week | B1: Theme | C1: Goal | D1: Unit | E1: Topic | F1: Reading | G1: Video | H1: GeeksForGeeks | I1: Date | J1: Progress
A2: 1 | B2: Fundamentals of Scalability & Reliability | C2: Understand basic concepts of building scalable and reliable systems. | D2: 1 | E2: Introduction to System Design Interviews | F2: What is System Design? Interview expectations (e.g. GDD Introduction, Alex Xu Vol 1 Chapter 1) | G2: NeetCode System Design Intro
D3: 2 | E3: Vertical vs. Horizontal Scaling & Load Balancers | F3: Concepts of scaling, types of load balancers (L4, L7), their roles | G3: Gaurav Sen/ByteByteGo on Load Balancers
D4: 3 | E4: Caching Basics | F4: Why cache? Where to cache? Cache hit/miss | G4: NeetCode Caching System Design | H4: Caching in Web Applications
D5: 4 | E5: Databases - SQL vs NoSQL | F5: Core differences, use cases for each. ACID vs. BASE. | G5: Explain SQL vs NoSQL (e.g. freeCodeCamp, ByteByteGo)
D6: 5 | E6: Week 1 Review & Q&A | F6: Review notes. Self-quiz on key terms (scalability, load balancing, caching, SQL/NoSQL). Consider a very simple system design: How would you design a simple counter that scales?
A7: 2 | B7: Data Storage & Distribution | C7: Dive deeper into database scaling, sharding, and replication. | D7: 1 | E7: Database Replication (Master-Slave, Master-Master) | F7: Why replication? Different replication strategies, advantages/disadvanges. | G7: Database Replication Explained
D8: 2 | E8: Sharding/Partitioning | F8: Why shard? Sharding strategies (hash-based, range-based, directory-based) | G8: ByteByteGo on Sharding
D9: 3 | E9: CDN (Content Delivery Network) | F9: What is a CDN? How does it work? Benefits | G9: NeetCode CDN System Design
D10: 4 | E10: Storage Solutions (Object Storage - S3 Concepts) | F10: Introduction to object storage vs. block/file sotrage. When to use S3. | G10: Concepts of Object Storage
D11: 5 | E11: Week 2 Review & Apply | F11: Review notes on data distribution. Problem: Design a simple photo storage service. How would you store photos? How would you retrieve them? (Focus on storage & CDN).
A12: 3 | B12: Communication & Asynchronous Processing | C12: Understand how different system components communicate and handle asynchronous tasks. | D12: 1 | E12: APIs (REST vs. GraphQL Basics) | F12: Principles of RESTful APIs, basic GraphQL concepts | G12: REST vs GraphQL overview
D13: 2 | E13: Message Queues (Kafka, RabbitMQ concepts) | F13: Why message queues? Producer-consumer model, benefits (decoupling, asynch) | G13: NeetCode Message Queue System Design
D14: 3 | E14: Pub-Sub Systems | F14: Publish-Subscribe pattern, differences from simple message queues | G14: Pub/Sub Explained
D15: 4 | E15: Distributed Caching (Memcached, Redis concepts) | F15: Caching at scale, consistency models for distributed caches | G15: Redis vs Memcached
D16: 5 | E16: Week 3 Review & Apply | F16: Review communication patterns. Problem: Design a system for processing user uploaded videos (focus on asynchronous processing via queues).
A17: 4 | B17: Search & Analytics | C17: Explore how search and analytics capabilities are built into large systems | D17: 1 | E17: Search Engines (Elasticsearch Concepts) | F17: How search engines work (inverted index, relevance scoring basics) | G17: Elasticsearch Explained
D18: 2 | E18: Logging, Monitoring & Alerting | F18: Why are these important? Tools/concepts (Prometheus, Grafana, ELK stack) | G18: System Monitoring Basics
D19: 3 | E19: Data Warehousing (DW) & OLAP vs. OLTP Basics | F19: Differences between transactional databases and analytical data warehouses | G19: OLTP vs OLAP
D20: 4 | E20: Data Streaming & Real-time Analytics (Kafka Streams / Spark Streaming concepts) | F20: Processing data in real-time vs. batch | G20: Introduction to Data Streaming
D21: 5 | E21: Week 4 Review & Apply | F21: Review new concepts. Problem: How would you add a search feature to an e-commerce website? (Focus on search engine integration)
A22: 5 | B22: Core System Design Patterns & Practice 1 | C22: Start applying concepts to classic system design problems | D22: 1 | E22: Design a URL Shortener (TinyURL). Focus: Hash generation, conflict resolution, database schema, scaling | F22: Grokking System Design (URL Shortener chapter) or Alex Xu Vol 1 | G22: NeetCode Design TinyURL
D23: 2 | E23: Design a Chat System (e.g., WhatsApp/Messenger). Focus: Real-time communication (WebSockets), message storage, fan-out | F23: Grokking System Design (Chat System chapter) or Alex Xu Vol 1 | G23: Gaurav Sen Design Chat System
D24: 3 | E24: Design Twitter/Facebook Feed. Focus: Fan-out on write vs. fan-out on read, timeline generation | F24: Grokking System Design (News Feed chapter) or Alex Xu Vol 1 | G24: ByteByteGo Design Twitter Feed
D25: 4 | E25: Design a Notification System. Focus: Different notification types, delivery mechanisms, queues | F25: Grokking System Design (Notification System chapter) or Alex Xu Vol 2 | G25: NeetCode Design Notification System
D26: 5 | E26: Week 5 Review & Self-Critique | F26: Review all problems designed this week. For one problem, try to identify what you might have missed or what alternative designs exist.
A27: 6 | B27: Advanced Concepts & Practice 2 | C27: Introduce more complex topics and apply them to challenging problems | D27: 1 | E27: Rate Limiter. Focus: Algorithms (Leaky Bucket, Token Bucket), distributed rate limiting | F27: Grokking System Design (Rate Limiter chapter) or Alex Xu Vol 1 | G27: NeetCode Design Rate Limiter
D28: 2 | E28: Distributed Unique ID Generator. Focus: Various approaches (UUID, database auto-increment, Twitter Snowflake) | F28: Grokking System Design (ID Generator chapter) or Alex Xu Vol 2 | G28: Alex Xu on Designing Unique ID Generator
D29: 3 | E29: Design Google Maps / Ride-Sharing App. Geohashing, real-time location updates, matching | F29: Grokking System Design (Google Maps/Uber chapter) or Alex Xu Vol 2 | G29: System Design Interview - Uber/Lyft
D30: 4 | E30: Design Netflix / Video Streaming Service. Focus: Video encoding, CDN, content delivery, DRM | F30: Grokking System Design (Netflix chapter) or Alex Xu Vol 2 | G30: Gaurav Sen Design Netflix
D31: 5 | E31: Week 6 Review & Optimize | F31: Review the complex designs. For one design, think about how you would optimize for cost or specific performance metrics.
A32: 7 | B32: Fault Tolerance, Consistency & Concurrency | C32: Understand how to build resilient systems and manage data consistency in distributed environments | D32: 1 | E32: CAP Theorem | F32: Understand Consistency, Availability, Partition Tolerance and the tradeoffs | G32: ByteByteGo CAP Theorem
D33: 2 | E33: Distributed Transactions & Two-Phase Commit (2PC) / Sagas (Concepts) | F33: How to ensure consistency across multiple services | G33: Distributed Transactions
D34: 3 | E34: Consensus Algorithms (Paxos/Raft - High Level) | F34: How distributed systems agree on a single value. (High level understanding, no deep dive needed) | G34: Raft Consensus Algorithm Explained
D35: 4 | E35: Leader Election | F35: How a leader is chosen in a distributed system | G35: Leader Election in Distributed Systems
D36: 5 | E36: Week 7 Review & Connect | F36: Review fault tolerance and consistency concepts. Think about previous designs (e.g., chat system): how would you ensure message message consistency if a server fails?
A37: 8 | B37: Final Practice & Mock Interviews | C37: Simulate interview conditions and identify remaining weaknesses | D37: 1 | E37: Design a Web Crawler / Search Engine Indexer. URL frontier, politeness, distributed crawling | F37: Grokking System Design (Web Crawler chapter) or Alex Xu Vol 2 | G37: System Design Interview - Web Crawler
D38: 2 | E38: Design Dropbox / Google Drive. Focus: File synchronization, versioning, conflict resolution | F38: Grokking System Design (Dropbox chapter) or Alex Xu Vol 1 | G38: Design Dropbox/Google Drive
D39: 3 | E39: Design a Recommendation System. Focus: Types of recommendations (collaborative filtering, content-based), data processing | F39: Grokking System Design (Recommendation System chapter) or Alex Xu Vol 2 | G39: Design Recommendation System
D40: 4 | E40: Mock Interview 1 (Self-Administered or Peer) | F40: Pick a random common system design problem (e.g., design a social network like Twitter, but simplified). Set a timer for 45-60 minutes. Go through the structured approach (clarify, estimate, HLD, deep dive, tradeoffs). Record yourself if possible, or have a friend listen.
D41: 5 | E41: Mock Interview 2 (Self-Administered or Peer) & Refinement | F41: Another mock interview. Try a different type of problem. Analyze your performance from both mocks. Where did you struggle? What concepts need more review? Identify 1-2 areas for future improvement.

Sheet Running (2025)
A1: Week | C1: Wed | E1: Thu | G1: Fri | I1: Sat | K1: Sun | M1: Mon | O1: Tue | S1: Tue | U1: Wed | W1: Thur | Y1: Fri | AA1: Sat | AC1: Sun | AE1: Mon
A2: 1 | B2: Base Training (Novice) | C2: 45672 | D2: 1.5 mi | E2: 45673 | F2: 3 mi | G2: 45674 | H2: 1.5 mi | I2: 45675 | J2: rest | K2: 45676 | L2: walk | M2: 45677 | N2: 3 mi | O2: 45678 | P2: rest | R2: Marathon Training (Novice) | S2: 45811 | T2: hike | U2: - | V2: 3 mi | W2: - | X2: 3 mi | Y2: 45814 | Z2: rest | AA2: 45815 | AB2: 6 mi | AC2: 45816 | AD2: cross | AE2: 45817 | AF2: rest
A3: 2 | C3: 45677 | D3: 1.5 mi | E3: 45680 | F3: 3 mi | G3: 45681 | H3: 1.5 mi | I3: 45682 | J3: rest | K3: 45683 | L3: walk | M3: 45684 | N3: 3.5 mi | O3: 45685 | P3: rest | S3: 45818 | T3: 3 mi | U3: 45819 | V3: 3 mi | W3: 45820 | X3: 3 mi | Y3: 45821 | Z3: rest | AA3: 45822 | AB3: 7 mi | AC3: 45823 | AD3: cross | AE3: 45824 | AF3: rest
A4: 3 | C4: 45686 | D4: 1.5 mi | E4: 45687 | F4: 3 mi | G4: 45688 | H4: 1.5 mi | I4: 45689 | J4: rest | K4: 45690 | L4: board | M4: 45691 | N4: 3 mi | O4: 45692 | P4: rest | S4: 45825 | T4: 3 mi | U4: - | V4: 4 mi | W4: - | X4: 3 mi | Y4: 45828 | Z4: rest | AA4: 45829 | AB4: cross | AC4: 45830 | AD4: 10K | AE4: 45831 | AF4: rest
A5: 4 | C5: 45707 | D5: 2 mi | E5: 45709 | F5: 3 mi | G5: 45710 | H5: 1.5 mi | I5: 45711 | J5: rest | K5: - | L5: walk | M5: 45712 | N5: 4 mi | O5: 45713 | P5: rest | S5: 45832 | T5: 3 mi | U5: 45833 | V5: 4 mi | W5: 45834 | X5: 3 mi | Y5: 45835 | Z5: rest | AA5: 45836 | AB5: 9 mi | AC5: 45837 | AD5: cross | AE5: 45838 | AF5: rest
A6: 5 | C6: 45714 | D6: 2 mi | E6: 45715 | F6: 3 mi | G6: 45716 | H6: 2 mi | I6: 45717 | J6: rest | K6: 45718 | L6: walk | M6: 45719 | N6: 3 mi | O6: 45720 | P6: rest | S6: 45839 | T6: 3 mi | U6: 45840 | V6: 5 mi | W6: 45841 | X6: 3 mi | Y6: 45842 | Z6: rest | AA6: 45843 | AB6: 10 mi | AC6: 45844 | AD6: cross | AE6: 45845 | AF6: rest
A7: 6 | C7: 45721 | D7: 2 mi | E7: 45722 | F7: 3 mi | G7: 45723 | H7: 2 mi | I7: 45724 | J7: rest | K7: 45725 | L7: walk | M7: 45727 | N7: 4.5 mi | O7: 45728 | P7: rest | S7: 45846 | T7: 3 mi | U7: - | V7: 5 mi | W7: 45848 | X7: 3 mi | Y7: 45849 | Z7: rest | AA7: 45850 | AB7: 7 mi | AC7: 45851 | AD7: cross | AE7: 45852 | AF7: rest
A8: 7 | C8: 45763 | D8: 2 mi | E8: 45764 | F8: 3 mi | G8: 45765 | H8: 2 mi | I8: 45766 | J8: rest | K8: 45767 | L8: walk | M8: 45768 | N8: 3 mi | O8: 45769 | P8: rest | S8: 45853 | T8: 3 mi | U8: 45854 | V8: 6 mi | W8: - | X8: 3 mi | Y8: 45856 | Z8: rest | AA8: 45857 | AB8: 12 mi | AC8: 45858 | AD8: cross | AE8: 45859 | AF8: rest
A9: 8 | C9: 45770 | D9: 2.5 mi | E9: 45771 | F9: 3 mi | G9: - | H9: 2 mi | I9: 45773 | J9: rest | K9: 45774 | L9: run | M9: 45775 | N9: 5 mi | O9: 45776 | P9: rest | S9: 45860 | T9: 3 mi | U9: - | V9: 6 mi | W9: 45862 | X9: 3 mi | Y9: 45863 | Z9: rest | AA9: 45864 | AB9: rest | AC9: 45865 | AD9: half marathon
A10: 9 | C10: 45784 | D10: 2.5 mi | E10: 45785 | F10: 3 mi | G10: - | H10: 2.5 mi | I10: 45787 | J10: rest | K10: 45788 | L10: run | M10: 45789 | N10: 3 mi | O10: 45790 | P10: rest
A11: 10 | C11: 45791 | D11: 2.5 mi | E11: 45792 | F11: 3 mi | G11: 45793 | H11: 2.5 mi | I11: 45794 | J11: rest | K11: 45795 | L11: ringfit | M11: 45796 | N11: 5.5 mi | O11: 45797 | P11: rest
A12: 11 | C12: 45798 | D12: 3 mi | E12: 45799 | F12: 3 mi | G12: 45800 | H12: hike | I12: 45801 | J12: rest | K12: 45802 | L12: ringfit | M12: 45803 | N12: 3 mi | O12: 45804 | P12: rest
A13: 12 | C13: 45805 | D13: 3 mi | E13: 45806 | F13: 3 mi | G13: 45807 | H13: 3 mi | I13: 45808 | J13: rest | K13: 45809 | L13: ringfit | M13: 45810 | N13: 6 mi
A14: 13
A15: 14
A16: 15
A17: 16
A18: 17
A19: 18
B23: Training Log
B27: Trail running routes
B28: San Bruno Mountain via Summit loop and Dairy Ravine Trail (3.6 mi)
B29: Mussel Rock Trail (2 mi)
B30: San Bruno Mountain Summit Loop Trail via Royce Way (4.7 mi)
B31: San Bruno Views Loop from Westlake (6.83 mi)

Sheet Friends
B1: January
A2: Huawei Chu | B2: Sent happy new year on IG. Told me he's going to SPIE on 2/23-2/27. Asked if any of our old friends will attend. Planning to meet him.
A3: Farah Huq | B3: She sent happy new year er. on FB Messenger. Told her I bought RAV4. She sent photo of her daughter (her "baby gremlin").
B4: She asked if I'm safe from wild fire on Messenger (I was in Snowbird for snowboarding at that time).
